{"Gini":{"2003":0.4690833194,"2004":0.4706776051,"2005":0.4622562652,"2006":0.4650935122,"2007":0.4637234565,"2008":0.4595042802,"2009":0.4591923671,"2010":0.4575027980,"2011":0.4548293765,"2012":0.4550938726},"Lorenz":{"LorenzTranches":{"2003":[{"Key":0.0,"Value":0.0},{"Key":0.35234,"Value":0.09092},{"Key":0.43282,"Value":0.13678},{"Key":0.50980,"Value":0.18887},{"Key":0.57697,"Value":0.24110},{"Key":0.63286,"Value":0.29041},{"Key":0.67954,"Value":0.33642},{"Key":0.77064,"Value":0.44370},{"Key":0.83972,"Value":0.54365},{"Key":0.91670,"Value":0.68500},{"Key":0.95308,"Value":0.77208},{"Key":0.99113,"Value":0.90598},{"Key":1.00001,"Value":1.00001}],"2004":[{"Key":0.0,"Value":0.0},{"Key":0.34264,"Value":0.08538},{"Key":0.42346,"Value":0.13071},{"Key":0.49963,"Value":0.18138},{"Key":0.56905,"Value":0.23446},{"Key":0.62554,"Value":0.28345},{"Key":0.67327,"Value":0.32972},{"Key":0.76387,"Value":0.43448},{"Key":0.83400,"Value":0.53433},{"Key":0.91435,"Value":0.67926},{"Key":0.95198,"Value":0.76780},{"Key":0.99082,"Value":0.90121},{"Key":1.00001,"Value":1.00001}],"2005":[{"Key":0.0,"Value":0.0},{"Key":0.32565,"Value":0.07940},{"Key":0.40450,"Value":0.12298},{"Key":0.48053,"Value":0.17287},{"Key":0.55313,"Value":0.22750},{"Key":0.61186,"Value":0.27765},{"Key":0.66154,"Value":0.32503},{"Key":0.75405,"Value":0.43015},{"Key":0.82727,"Value":0.53270},{"Key":0.91113,"Value":0.68163},{"Key":0.95074,"Value":0.77327},{"Key":0.99107,"Value":0.90949},{"Key":1.00001,"Value":1.00001}],"2006":[{"Key":0.0,"Value":0.0},{"Key":0.31564,"Value":0.07416},{"Key":0.39175,"Value":0.11506},{"Key":0.46585,"Value":0.16224},{"Key":0.53953,"Value":0.21603},{"Key":0.60014,"Value":0.26619},{"Key":0.65011,"Value":0.31240},{"Key":0.74297,"Value":0.41443},{"Key":0.81750,"Value":0.51562},{"Key":0.90544,"Value":0.66710},{"Key":0.94724,"Value":0.76089},{"Key":0.99081,"Value":0.90351},{"Key":1.00001,"Value":1.00001}],"2007":[{"Key":0.0,"Value":0.0},{"Key":0.30520,"Value":0.06897},{"Key":0.37833,"Value":0.10739},{"Key":0.45007,"Value":0.15202},{"Key":0.52416,"Value":0.20492},{"Key":0.58646,"Value":0.25529},{"Key":0.63737,"Value":0.30134},{"Key":0.73222,"Value":0.40317},{"Key":0.80747,"Value":0.50306},{"Key":0.89875,"Value":0.65683},{"Key":0.94339,"Value":0.75466},{"Key":0.99007,"Value":0.90422},{"Key":1.00001,"Value":1.00001}],"2008":[{"Key":0.0,"Value":0.0},{"Key":0.29473,"Value":0.06457},{"Key":0.36394,"Value":0.10013},{"Key":0.43255,"Value":0.14170},{"Key":0.50631,"Value":0.19328},{"Key":0.57038,"Value":0.24398},{"Key":0.62227,"Value":0.28990},{"Key":0.71887,"Value":0.39101},{"Key":0.79621,"Value":0.49148},{"Key":0.89157,"Value":0.64887},{"Key":0.93883,"Value":0.75031},{"Key":0.98968,"Value":0.90990},{"Key":1.00001,"Value":1.00001}],"2009":[{"Key":0.0,"Value":0.0},{"Key":0.29246,"Value":0.06239},{"Key":0.36031,"Value":0.09693},{"Key":0.42595,"Value":0.13637},{"Key":0.49876,"Value":0.18688},{"Key":0.56276,"Value":0.23709},{"Key":0.61453,"Value":0.28251},{"Key":0.71189,"Value":0.38345},{"Key":0.78970,"Value":0.48367},{"Key":0.88695,"Value":0.64267},{"Key":0.93649,"Value":0.74808},{"Key":0.98995,"Value":0.91424},{"Key":1.00001,"Value":1.00001}],"2010":[{"Key":0.0,"Value":0.0},{"Key":0.30962,"Value":0.06965},{"Key":0.38243,"Value":0.10824},{"Key":0.48887,"Value":0.17776},{"Key":0.63690,"Value":0.30105},{"Key":0.79829,"Value":0.49251},{"Key":0.93685,"Value":0.74499},{"Key":0.98970,"Value":0.90938},{"Key":1.00001,"Value":1.00001}],"2011":[{"Key":0.0,"Value":0.0},{"Key":0.29015,"Value":0.06205},{"Key":0.36012,"Value":0.09760},{"Key":0.46559,"Value":0.16369},{"Key":0.61645,"Value":0.28416},{"Key":0.78287,"Value":0.47352},{"Key":0.93078,"Value":0.73246},{"Key":0.98880,"Value":0.90565},{"Key":1.00001,"Value":1.00001}],"2012":[{"Key":0.0,"Value":0.0},{"Key":0.28308,"Value":0.05839},{"Key":0.35130,"Value":0.09241},{"Key":0.45446,"Value":0.15578},{"Key":0.60772,"Value":0.27595},{"Key":0.77423,"Value":0.46173},{"Key":0.92583,"Value":0.72226},{"Key":0.98803,"Value":0.90443},{"Key":1.00001,"Value":1.00001}]},"LorenzDeciles":{"2003":[{"Key":0.0,"Value":0.0},{"Key":0.05,"Value":0.0129},{"Key":0.10,"Value":0.0258},{"Key":0.15,"Value":0.0387},{"Key":0.20,"Value":0.0516},{"Key":0.25,"Value":0.0645},{"Key":0.30,"Value":0.0774},{"Key":0.35,"Value":0.0903},{"Key":0.40,"Value":0.1181},{"Key":0.45,"Value":0.1484},{"Key":0.50,"Value":0.1822},{"Key":0.55,"Value":0.2201},{"Key":0.60,"Value":0.2614},{"Key":0.65,"Value":0.3073},{"Key":0.70,"Value":0.3605},{"Key":0.75,"Value":0.4194},{"Key":0.80,"Value":0.4862},{"Key":0.85,"Value":0.5625},{"Key":0.90,"Value":0.6543},{"Key":0.95,"Value":0.7647},{"Key":1.00,"Value":0.9999}],"2004":[{"Key":0.0,"Value":0.0},{"Key":0.05,"Value":0.0125},{"Key":0.10,"Value":0.0249},{"Key":0.15,"Value":0.0374},{"Key":0.20,"Value":0.0498},{"Key":0.25,"Value":0.0623},{"Key":0.30,"Value":0.0748},{"Key":0.35,"Value":0.0895},{"Key":0.40,"Value":0.1176},{"Key":0.45,"Value":0.1484},{"Key":0.50,"Value":0.1817},{"Key":0.55,"Value":0.2199},{"Key":0.60,"Value":0.2613},{"Key":0.65,"Value":0.3072},{"Key":0.70,"Value":0.3606},{"Key":0.75,"Value":0.4184},{"Key":0.80,"Value":0.4859},{"Key":0.85,"Value":0.5632},{"Key":0.90,"Value":0.6534},{"Key":0.95,"Value":0.7631},{"Key":1.00,"Value":0.9999}],"2005":[{"Key":0.0,"Value":0.0},{"Key":0.05,"Value":0.0122},{"Key":0.10,"Value":0.0244},{"Key":0.15,"Value":0.0366},{"Key":0.20,"Value":0.0488},{"Key":0.25,"Value":0.0610},{"Key":0.30,"Value":0.0731},{"Key":0.35,"Value":0.0929},{"Key":0.40,"Value":0.1205},{"Key":0.45,"Value":0.1528},{"Key":0.50,"Value":0.1875},{"Key":0.55,"Value":0.2251},{"Key":0.60,"Value":0.2675},{"Key":0.65,"Value":0.3140},{"Key":0.70,"Value":0.3687},{"Key":0.75,"Value":0.4255},{"Key":0.80,"Value":0.4945},{"Key":0.85,"Value":0.5731},{"Key":0.90,"Value":0.6619},{"Key":0.95,"Value":0.7716},{"Key":1.00,"Value":0.9999}],"2006":[{"Key":0.0,"Value":0.0},{"Key":0.05,"Value":0.0117},{"Key":0.10,"Value":0.0235},{"Key":0.15,"Value":0.0352},{"Key":0.20,"Value":0.0470},{"Key":0.25,"Value":0.0587},{"Key":0.30,"Value":0.0705},{"Key":0.35,"Value":0.0926},{"Key":0.40,"Value":0.1203},{"Key":0.45,"Value":0.1521},{"Key":0.50,"Value":0.1872},{"Key":0.55,"Value":0.2247},{"Key":0.60,"Value":0.2661},{"Key":0.65,"Value":0.3123},{"Key":0.70,"Value":0.3672},{"Key":0.75,"Value":0.4240},{"Key":0.80,"Value":0.4919},{"Key":0.85,"Value":0.5716},{"Key":0.90,"Value":0.6577},{"Key":0.95,"Value":0.7699},{"Key":1.00,"Value":0.9999}],"2007":[{"Key":0.0,"Value":0.0},{"Key":0.05,"Value":0.0113},{"Key":0.10,"Value":0.0226},{"Key":0.15,"Value":0.0339},{"Key":0.20,"Value":0.0452},{"Key":0.25,"Value":0.0565},{"Key":0.30,"Value":0.0678},{"Key":0.35,"Value":0.0925},{"Key":0.40,"Value":0.1209},{"Key":0.45,"Value":0.1520},{"Key":0.50,"Value":0.1877},{"Key":0.55,"Value":0.2258},{"Key":0.60,"Value":0.2675},{"Key":0.65,"Value":0.3149},{"Key":0.70,"Value":0.3686},{"Key":0.75,"Value":0.4268},{"Key":0.80,"Value":0.4931},{"Key":0.85,"Value":0.5747},{"Key":0.90,"Value":0.6596},{"Key":0.95,"Value":0.7758},{"Key":1.00,"Value":0.9999}],"2008":[{"Key":0.0,"Value":0.0},{"Key":0.05,"Value":0.0110},{"Key":0.10,"Value":0.0219},{"Key":0.15,"Value":0.0329},{"Key":0.20,"Value":0.0438},{"Key":0.25,"Value":0.0548},{"Key":0.30,"Value":0.0673},{"Key":0.35,"Value":0.0930},{"Key":0.40,"Value":0.1220},{"Key":0.45,"Value":0.1539},{"Key":0.50,"Value":0.1889},{"Key":0.55,"Value":0.2279},{"Key":0.60,"Value":0.2702},{"Key":0.65,"Value":0.3189},{"Key":0.70,"Value":0.3713},{"Key":0.75,"Value":0.4315},{"Key":0.80,"Value":0.4977},{"Key":0.85,"Value":0.5803},{"Key":0.90,"Value":0.6670},{"Key":0.95,"Value":0.7854},{"Key":1.00,"Value":0.9999}],"2009":[{"Key":0.0,"Value":0.0},{"Key":0.05,"Value":0.0107},{"Key":0.10,"Value":0.0213},{"Key":0.15,"Value":0.0320},{"Key":0.20,"Value":0.0427},{"Key":0.25,"Value":0.0533},{"Key":0.30,"Value":0.0662},{"Key":0.35,"Value":0.0917},{"Key":0.40,"Value":0.1208},{"Key":0.45,"Value":0.1531},{"Key":0.50,"Value":0.1879},{"Key":0.55,"Value":0.2271},{"Key":0.60,"Value":0.2698},{"Key":0.65,"Value":0.3193},{"Key":0.70,"Value":0.3711},{"Key":0.75,"Value":0.4325},{"Key":0.80,"Value":0.5005},{"Key":0.85,"Value":0.5823},{"Key":0.90,"Value":0.6704},{"Key":0.95,"Value":0.7901},{"Key":1.00,"Value":0.9999}],"2010":[{"Key":0.0,"Value":0.0},{"Key":0.05,"Value":0.0112},{"Key":0.10,"Value":0.0225},{"Key":0.15,"Value":0.0337},{"Key":0.20,"Value":0.0450},{"Key":0.25,"Value":0.0562},{"Key":0.30,"Value":0.0675},{"Key":0.35,"Value":0.0911},{"Key":0.40,"Value":0.1197},{"Key":0.45,"Value":0.1524},{"Key":0.50,"Value":0.1870},{"Key":0.55,"Value":0.2287},{"Key":0.60,"Value":0.2703},{"Key":0.65,"Value":0.3166},{"Key":0.70,"Value":0.3759},{"Key":0.75,"Value":0.4352},{"Key":0.80,"Value":0.4956},{"Key":0.85,"Value":0.5867},{"Key":0.90,"Value":0.6778},{"Key":0.95,"Value":0.7859},{"Key":1.00,"Value":0.9999}],"2011":[{"Key":0.0,"Value":0.0},{"Key":0.05,"Value":0.0107},{"Key":0.10,"Value":0.0214},{"Key":0.15,"Value":0.0321},{"Key":0.20,"Value":0.0428},{"Key":0.25,"Value":0.0535},{"Key":0.30,"Value":0.0671},{"Key":0.35,"Value":0.0925},{"Key":0.40,"Value":0.1226},{"Key":0.45,"Value":0.1539},{"Key":0.50,"Value":0.1912},{"Key":0.55,"Value":0.2311},{"Key":0.60,"Value":0.2710},{"Key":0.65,"Value":0.3223},{"Key":0.70,"Value":0.3792},{"Key":0.75,"Value":0.4361},{"Key":0.80,"Value":0.5035},{"Key":0.85,"Value":0.5910},{"Key":0.90,"Value":0.6786},{"Key":0.95,"Value":0.7898},{"Key":1.00,"Value":0.9999}],"2012":[{"Key":0.0,"Value":0.0},{"Key":0.05,"Value":0.0103},{"Key":0.10,"Value":0.0206},{"Key":0.15,"Value":0.0309},{"Key":0.20,"Value":0.0413},{"Key":0.25,"Value":0.0516},{"Key":0.30,"Value":0.0668},{"Key":0.35,"Value":0.0918},{"Key":0.40,"Value":0.1223},{"Key":0.45,"Value":0.1530},{"Key":0.50,"Value":0.1915},{"Key":0.55,"Value":0.2307},{"Key":0.60,"Value":0.2699},{"Key":0.65,"Value":0.3231},{"Key":0.70,"Value":0.3789},{"Key":0.75,"Value":0.4347},{"Key":0.80,"Value":0.5060},{"Key":0.85,"Value":0.5919},{"Key":0.90,"Value":0.6779},{"Key":0.95,"Value":0.7930},{"Key":1.00,"Value":0.9999}]}},"Moyennes":{"2003":14424.0,"2004":14679.0,"2005":14913.0,"2006":19241.0,"2007":19680.0,"2008":20113.0,"2009":20291.0,"2010":20768.0,"2011":21671.0,"2012":22089.0},"Numero":"300","Nom":"GARD","Data":{"2003":{"depNumber":"300","depName":"GARD","year":2003,"tranches":[{"trancheName":"0 à 7 500","trancheMin":0,"trancheMax":7500,"nbFoyers":130343,"nbFoyersImposables":1832,"revenus":485202236,"revenusImposables":7878218,"impot":-9520395,"nbFoyers_salaires":63718,"revenus_salaires":439279198,"nbFoyers_retraites":43114,"revenus_retraites":329287645},{"trancheName":"7 501 à 9 000","trancheMin":7501,"trancheMax":9000,"nbFoyers":29774,"nbFoyersImposables":7612,"revenus":244726948,"revenusImposables":65041469,"impot":-5061021,"nbFoyers_salaires":21887,"revenus_salaires":261018476,"nbFoyers_retraites":8129,"revenus_retraites":93365867},{"trancheName":"9 001 à 10 500","trancheMin":9001,"trancheMax":10500,"nbFoyers":28476,"nbFoyersImposables":12566,"revenus":277967596,"revenusImposables":122484942,"impot":954436,"nbFoyers_salaires":19423,"revenus_salaires":269414309,"nbFoyers_retraites":9397,"revenus_retraites":125055920},{"trancheName":"10 501 à 12 000","trancheMin":10501,"trancheMax":12000,"nbFoyers":24847,"nbFoyersImposables":12357,"revenus":278702036,"revenusImposables":138856333,"impot":4987107,"nbFoyers_salaires":15676,"revenus_salaires":244430692,"nbFoyers_retraites":9718,"revenus_retraites":144877433},{"trancheName":"12 001 à 13500","trancheMin":12001,"trancheMax":13500,"nbFoyers":20677,"nbFoyersImposables":12043,"revenus":263111349,"revenusImposables":153832240,"impot":6009785,"nbFoyers_salaires":13175,"revenus_salaires":228738597,"nbFoyers_retraites":8145,"revenus_retraites":133617725},{"trancheName":"13501 à 15 000","trancheMin":13501,"trancheMax":15000,"nbFoyers":17267,"nbFoyersImposables":12350,"revenus":245509747,"revenusImposables":175740778,"impot":7128917,"nbFoyers_salaires":11347,"revenus_salaires":216673623,"nbFoyers_retraites":6715,"revenus_retraites":117181559},{"trancheName":"15 001 à 19 000","trancheMin":15001,"trancheMax":19000,"nbFoyers":33703,"nbFoyersImposables":27785,"revenus":572485145,"revenusImposables":473819762,"impot":22040467,"nbFoyers_salaires":23564,"revenus_salaires":523262820,"nbFoyers_retraites":12086,"revenus_retraites":230848737},{"trancheName":"19 001 à 23 000","trancheMin":19001,"trancheMax":23000,"nbFoyers":25555,"nbFoyersImposables":23501,"revenus":533347090,"revenusImposables":491034385,"impot":27661112,"nbFoyers_salaires":17066,"revenus_salaires":458374870,"nbFoyers_retraites":10145,"revenus_retraites":230149996},{"trancheName":"23 001 à 31 000","trancheMin":23001,"trancheMax":31000,"nbFoyers":28477,"nbFoyersImposables":27543,"revenus":754300704,"revenusImposables":730191895,"impot":53079710,"nbFoyers_salaires":20169,"revenus_salaires":666430717,"nbFoyers_retraites":10384,"revenus_retraites":271570322},{"trancheName":"31 001 à 39 000","trancheMin":31001,"trancheMax":39000,"nbFoyers":13458,"nbFoyersImposables":13250,"revenus":464662070,"revenusImposables":457481381,"impot":44498685,"nbFoyers_salaires":9523,"revenus_salaires":387447202,"nbFoyers_retraites":4801,"revenus_retraites":150653914},{"trancheName":"39 001 à 78 000","trancheMin":39001,"trancheMax":78000,"nbFoyers":14076,"nbFoyersImposables":13900,"revenus":714507543,"revenusImposables":705665641,"impot":97866615,"nbFoyers_salaires":9997,"revenus_salaires":509817360,"nbFoyers_retraites":4248,"revenus_retraites":152641595},{"trancheName":"+ de 78 000","trancheMin":78000,"trancheMax":0,"nbFoyers":3283,"nbFoyersImposables":3269,"revenus":501796240,"revenusImposables":500200593,"impot":111428159,"nbFoyers_salaires":2293,"revenus_salaires":156946509,"nbFoyers_retraites":606,"revenus_retraites":23014407}],"nbFoyers":369936,"nbFoyersImposables":168008,"revenus":5336318704,"revenusImposables":4022227637,"impot":361073577,"nbFoyers_salaires":227838,"revenus_salaires":4361834373,"nbFoyers_retraites":127488,"revenus_retraites":2002265120},"2004":{"depNumber":"300","depName":"GARD","year":2004,"tranches":[{"trancheName":"0 à 7 500","trancheMin":0,"trancheMax":7500,"nbFoyers":128680,"nbFoyersImposables":1878,"revenus":470714638,"revenusImposables":7847712,"impot":-9558974,"nbFoyers_salaires":61659,"revenus_salaires":424696436,"nbFoyers_retraites":42616,"revenus_retraites":329653146},{"trancheName":"7 501 à 9 000","trancheMin":7501,"trancheMax":9000,"nbFoyers":30352,"nbFoyersImposables":6307,"revenus":249928088,"revenusImposables":54359935,"impot":-5698407,"nbFoyers_salaires":21775,"revenus_salaires":262118185,"nbFoyers_retraites":8836,"revenus_retraites":104261115},{"trancheName":"9 001 à 10 500","trancheMin":9001,"trancheMax":10500,"nbFoyers":28606,"nbFoyersImposables":12980,"revenus":279321617,"revenusImposables":126268138,"impot":-297073,"nbFoyers_salaires":20375,"revenus_salaires":283144285,"nbFoyers_retraites":8704,"revenus_retraites":116913924},{"trancheName":"10 501 à 12 000","trancheMin":10501,"trancheMax":12000,"nbFoyers":26073,"nbFoyersImposables":12798,"revenus":292650961,"revenusImposables":143981335,"impot":4569942,"nbFoyers_salaires":16671,"revenus_salaires":260994737,"nbFoyers_retraites":9946,"revenus_retraites":149938874},{"trancheName":"12 001 à 13500","trancheMin":12001,"trancheMax":13500,"nbFoyers":21217,"nbFoyersImposables":12007,"revenus":270099049,"revenusImposables":153300582,"impot":6016590,"nbFoyers_salaires":13581,"revenus_salaires":236555284,"nbFoyers_retraites":8269,"revenus_retraites":137723303},{"trancheName":"13501 à 15 000","trancheMin":13501,"trancheMax":15000,"nbFoyers":17927,"nbFoyersImposables":12728,"revenus":255091221,"revenusImposables":181234103,"impot":7128290,"nbFoyers_salaires":11498,"revenus_salaires":219764579,"nbFoyers_retraites":7294,"revenus_retraites":130662468},{"trancheName":"15 001 à 19 000","trancheMin":15001,"trancheMax":19000,"nbFoyers":34025,"nbFoyersImposables":27903,"revenus":577546251,"revenusImposables":475354401,"impot":21412545,"nbFoyers_salaires":23754,"revenus_salaires":529195472,"nbFoyers_retraites":12284,"revenus_retraites":237939989},{"trancheName":"19 001 à 23 000","trancheMin":19001,"trancheMax":23000,"nbFoyers":26339,"nbFoyersImposables":23981,"revenus":550478150,"revenusImposables":501742156,"impot":27608970,"nbFoyers_salaires":17451,"revenus_salaires":470394666,"nbFoyers_retraites":10832,"revenus_retraites":247581542},{"trancheName":"23 001 à 31 000","trancheMin":23001,"trancheMax":31000,"nbFoyers":30176,"nbFoyersImposables":29066,"revenus":799021926,"revenusImposables":770319514,"impot":54669348,"nbFoyers_salaires":21342,"revenus_salaires":707996236,"nbFoyers_retraites":11365,"revenus_retraites":301763652},{"trancheName":"31 001 à 39 000","trancheMin":31001,"trancheMax":39000,"nbFoyers":14133,"nbFoyersImposables":13874,"revenus":488100519,"revenusImposables":479170265,"impot":46131895,"nbFoyers_salaires":10032,"revenus_salaires":412577681,"nbFoyers_retraites":5167,"revenus_retraites":163899379},{"trancheName":"39 001 à 78 000","trancheMin":39001,"trancheMax":78000,"nbFoyers":14588,"nbFoyersImposables":14420,"revenus":735487005,"revenusImposables":727211121,"impot":98581407,"nbFoyers_salaires":10386,"revenus_salaires":542748077,"nbFoyers_retraites":4548,"revenus_retraites":170856094},{"trancheName":"+ de 78 000","trancheMin":78000,"trancheMax":0,"nbFoyers":3441,"nbFoyersImposables":-1,"revenus":544567468,"revenusImposables":-1,"impot":117630273,"nbFoyers_salaires":2408,"revenus_salaires":172158423,"nbFoyers_retraites":668,"revenus_retraites":25040716}],"nbFoyers":375557,"nbFoyersImposables":171373,"revenus":5513006893,"revenusImposables":4160557632,"impot":368194806,"nbFoyers_salaires":230932,"revenus_salaires":4522344061,"nbFoyers_retraites":130529,"revenus_retraites":2116234202},"2005":{"depNumber":"300","depName":"GARD","year":2005,"tranches":[{"trancheName":"0 à 7 500","trancheMin":0,"trancheMax":7500,"nbFoyers":124111,"nbFoyersImposables":4082,"revenus":451286550,"revenusImposables":16144750,"impot":-10342579,"nbFoyers_salaires":59621,"revenus_salaires":396780035,"nbFoyers_retraites":42454,"revenus_retraites":331265679},{"trancheName":"7 501 à 9 000","trancheMin":7501,"trancheMax":9000,"nbFoyers":30052,"nbFoyersImposables":5055,"revenus":247700428,"revenusImposables":43579895,"impot":-6461392,"nbFoyers_salaires":20914,"revenus_salaires":250473047,"nbFoyers_retraites":9680,"revenus_retraites":114728781},{"trancheName":"9 001 à 10 500","trancheMin":9001,"trancheMax":10500,"nbFoyers":28977,"nbFoyersImposables":13948,"revenus":283556760,"revenusImposables":135977200,"impot":-2060884,"nbFoyers_salaires":21003,"revenus_salaires":290773565,"nbFoyers_retraites":8584,"revenus_retraites":114652752},{"trancheName":"10 501 à 12 000","trancheMin":10501,"trancheMax":12000,"nbFoyers":27669,"nbFoyersImposables":13968,"revenus":310533974,"revenusImposables":157113217,"impot":3930007,"nbFoyers_salaires":17937,"revenus_salaires":279856642,"nbFoyers_retraites":10584,"revenus_retraites":160278143},{"trancheName":"12 001 à 13500","trancheMin":12001,"trancheMax":13500,"nbFoyers":22385,"nbFoyersImposables":12783,"revenus":285053737,"revenusImposables":163046191,"impot":5937238,"nbFoyers_salaires":14527,"revenus_salaires":251993426,"nbFoyers_retraites":8836,"revenus_retraites":146202056},{"trancheName":"13501 à 15 000","trancheMin":13501,"trancheMax":15000,"nbFoyers":18933,"nbFoyersImposables":13434,"revenus":269279877,"revenusImposables":191215277,"impot":7097914,"nbFoyers_salaires":12171,"revenus_salaires":231322506,"nbFoyers_retraites":7800,"revenus_retraites":140216244},{"trancheName":"15 001 à 19 000","trancheMin":15001,"trancheMax":19000,"nbFoyers":35259,"nbFoyersImposables":28771,"revenus":597503924,"revenusImposables":489346149,"impot":20739155,"nbFoyers_salaires":24601,"revenus_salaires":542008462,"nbFoyers_retraites":13202,"revenus_retraites":255983982},{"trancheName":"19 001 à 23 000","trancheMin":19001,"trancheMax":23000,"nbFoyers":27906,"nbFoyersImposables":25452,"revenus":582907916,"revenusImposables":532157145,"impot":27535092,"nbFoyers_salaires":18485,"revenus_salaires":493050950,"nbFoyers_retraites":11782,"revenus_retraites":270770470},{"trancheName":"23 001 à 31 000","trancheMin":23001,"trancheMax":31000,"nbFoyers":31960,"nbFoyersImposables":30722,"revenus":846483632,"revenusImposables":814572064,"impot":55391605,"nbFoyers_salaires":22633,"revenus_salaires":744554811,"nbFoyers_retraites":12564,"revenus_retraites":334760988},{"trancheName":"31 001 à 39 000","trancheMin":31001,"trancheMax":39000,"nbFoyers":15096,"nbFoyersImposables":14801,"revenus":520884453,"revenusImposables":510819755,"impot":47492948,"nbFoyers_salaires":10730,"revenus_salaires":442017697,"nbFoyers_retraites":5777,"revenus_retraites":185224409},{"trancheName":"39 001 à 78 000","trancheMin":39001,"trancheMax":78000,"nbFoyers":15369,"nbFoyersImposables":15115,"revenus":774258131,"revenusImposables":761555476,"impot":103909423,"nbFoyers_salaires":10980,"revenus_salaires":585021075,"nbFoyers_retraites":5096,"revenus_retraites":192783144},{"trancheName":"+ de 78 000","trancheMin":78000,"trancheMax":0,"nbFoyers":3404,"nbFoyersImposables":3380,"revenus":514505314,"revenusImposables":511199709,"impot":121940521,"nbFoyers_salaires":2373,"revenus_salaires":184993257,"nbFoyers_retraites":700,"revenus_retraites":27043292}],"nbFoyers":381121,"nbFoyersImposables":181511,"revenus":5683954696,"revenusImposables":4326726828,"impot":375109048,"nbFoyers_salaires":235975,"revenus_salaires":4692845473,"nbFoyers_retraites":137059,"revenus_retraites":2273909940},"2006":{"depNumber":"300","depName":"GARD","year":2006,"tranches":[{"trancheName":"0 à 9 400","trancheMin":0,"trancheMax":9400,"nbFoyers":122731,"nbFoyersImposables":1890,"revenus":554872792,"revenusImposables":9740391,"impot":-15952270,"nbFoyers_salaires":58263,"revenus_salaires":382583571,"nbFoyers_retraites":41648,"revenus_retraites":326434836},{"trancheName":"9 401 à 11 250","trancheMin":9401,"trancheMax":11250,"nbFoyers":29594,"nbFoyersImposables":3497,"revenus":306039962,"revenusImposables":38013206,"impot":-9213489,"nbFoyers_salaires":19956,"revenus_salaires":237655635,"nbFoyers_retraites":10208,"revenus_retraites":122598156},{"trancheName":"11 251 à 13 150","trancheMin":11251,"trancheMax":13150,"nbFoyers":28813,"nbFoyersImposables":14043,"revenus":352971976,"revenusImposables":171527578,"impot":-6623563,"nbFoyers_salaires":21492,"revenus_salaires":297465316,"nbFoyers_retraites":7893,"revenus_retraites":105471770},{"trancheName":"13 151 à 15 000","trancheMin":13151,"trancheMax":15000,"nbFoyers":28649,"nbFoyersImposables":14182,"revenus":402472327,"revenusImposables":199912446,"impot":528013,"nbFoyers_salaires":18907,"revenus_salaires":294563917,"nbFoyers_retraites":10612,"revenus_retraites":161764082},{"trancheName":"15 001 à 16 900","trancheMin":15001,"trancheMax":16900,"nbFoyers":23565,"nbFoyersImposables":13126,"revenus":375316409,"revenusImposables":209157491,"impot":4217264,"nbFoyers_salaires":15347,"revenus_salaires":264219343,"nbFoyers_retraites":9285,"revenus_retraites":153802111},{"trancheName":"16 901 à 18 750","trancheMin":16901,"trancheMax":18750,"nbFoyers":19430,"nbFoyersImposables":13493,"revenus":345751023,"revenusImposables":240305491,"impot":5064408,"nbFoyers_salaires":12378,"revenus_salaires":234220146,"nbFoyers_retraites":8189,"revenus_retraites":148584179},{"trancheName":"18 751 à 23 750","trancheMin":18751,"trancheMax":23750,"nbFoyers":36105,"nbFoyersImposables":28809,"revenus":763398464,"revenusImposables":611395255,"impot":14898636,"nbFoyers_salaires":25153,"revenus_salaires":553514514,"nbFoyers_retraites":13627,"revenus_retraites":266225925},{"trancheName":"23 751 à 28 750","trancheMin":23751,"trancheMax":28750,"nbFoyers":28981,"nbFoyersImposables":25988,"revenus":757060273,"revenusImposables":679530150,"impot":20696546,"nbFoyers_salaires":19111,"revenus_salaires":506778159,"nbFoyers_retraites":12459,"revenus_retraites":288965946},{"trancheName":"28 751 à 38 750","trancheMin":28751,"trancheMax":38750,"nbFoyers":34193,"nbFoyersImposables":32611,"revenus":1133333328,"revenusImposables":1082218711,"impot":49049121,"nbFoyers_salaires":24157,"revenus_salaires":792363980,"nbFoyers_retraites":13721,"revenus_retraites":370027535},{"trancheName":"38 751 à 48 750","trancheMin":38751,"trancheMax":48750,"nbFoyers":16254,"nbFoyersImposables":15823,"revenus":701702178,"revenusImposables":683239004,"impot":42392588,"nbFoyers_salaires":11600,"revenus_salaires":478941757,"nbFoyers_retraites":6295,"revenus_retraites":203123490},{"trancheName":"48 751 à 97 500","trancheMin":48751,"trancheMax":97500,"nbFoyers":16941,"nbFoyersImposables":16596,"revenus":1067045491,"revenusImposables":1045744398,"impot":100932598,"nbFoyers_salaires":12182,"revenus_salaires":654179747,"nbFoyers_retraites":5777,"revenus_retraites":220864167},{"trancheName":"+ de 97 500","trancheMin":97500,"trancheMax":0,"nbFoyers":3571,"nbFoyersImposables":3528,"revenus":721789249,"revenusImposables":713437988,"impot":133012690,"nbFoyers_salaires":2532,"revenus_salaires":207914539,"nbFoyers_retraites":757,"revenus_retraites":30619322}],"nbFoyers":388827,"nbFoyersImposables":183586,"revenus":7481753472,"revenusImposables":5684222109,"impot":339002542,"nbFoyers_salaires":241078,"revenus_salaires":4904400624,"nbFoyers_retraites":140471,"revenus_retraites":2398481519},"2007":{"depNumber":"300","depName":"GARD","year":2007,"tranches":[{"trancheName":"0 à 9 400","trancheMin":0,"trancheMax":9400,"nbFoyers":121217,"nbFoyersImposables":1832,"revenus":539134808,"revenusImposables":9422777,"impot":-16004272,"nbFoyers_salaires":56821,"revenus_salaires":373113257,"nbFoyers_retraites":40439,"revenus_retraites":318783752},{"trancheName":"9 401 à 11 250","trancheMin":9401,"trancheMax":11250,"nbFoyers":29044,"nbFoyersImposables":2678,"revenus":300291493,"revenusImposables":29192085,"impot":-8774005,"nbFoyers_salaires":19268,"revenus_salaires":231030380,"nbFoyers_retraites":10265,"revenus_retraites":124094053},{"trancheName":"11 251 à 13 150","trancheMin":11251,"trancheMax":13150,"nbFoyers":28495,"nbFoyersImposables":13510,"revenus":348818237,"revenusImposables":165199042,"impot":-6966089,"nbFoyers_salaires":21194,"revenus_salaires":296462463,"nbFoyers_retraites":7830,"revenus_retraites":104653812},{"trancheName":"13 151 à 15 000","trancheMin":13151,"trancheMax":15000,"nbFoyers":29426,"nbFoyersImposables":14703,"revenus":413531365,"revenusImposables":207364200,"impot":79477,"nbFoyers_salaires":19518,"revenus_salaires":305304334,"nbFoyers_retraites":10690,"revenus_retraites":163971276},{"trancheName":"15 001 à 16 900","trancheMin":15001,"trancheMax":16900,"nbFoyers":24743,"nbFoyersImposables":14184,"revenus":393729619,"revenusImposables":225831999,"impot":4578395,"nbFoyers_salaires":16150,"revenus_salaires":279511611,"nbFoyers_retraites":9647,"revenus_retraites":160744546},{"trancheName":"16 901 à 18 750","trancheMin":16901,"trancheMax":18750,"nbFoyers":20220,"nbFoyersImposables":13940,"revenus":359975967,"revenusImposables":248563757,"impot":5108341,"nbFoyers_salaires":12935,"revenus_salaires":245147019,"nbFoyers_retraites":8406,"revenus_retraites":153652915},{"trancheName":"18 751 à 23 750","trancheMin":18751,"trancheMax":23750,"nbFoyers":37674,"nbFoyersImposables":29969,"revenus":795986861,"revenusImposables":635816363,"impot":15808749,"nbFoyers_salaires":26087,"revenus_salaires":575533736,"nbFoyers_retraites":14366,"revenus_retraites":282574102},{"trancheName":"23 751 à 28 750","trancheMin":23751,"trancheMax":28750,"nbFoyers":29887,"nbFoyersImposables":26775,"revenus":780806182,"revenusImposables":700257165,"impot":21139429,"nbFoyers_salaires":19481,"revenus_salaires":519143141,"nbFoyers_retraites":13048,"revenus_retraites":304157987},{"trancheName":"28 751 à 38 750","trancheMin":28751,"trancheMax":38750,"nbFoyers":36254,"nbFoyersImposables":34657,"revenus":1201956819,"revenusImposables":1150314129,"impot":50189885,"nbFoyers_salaires":25136,"revenus_salaires":830202187,"nbFoyers_retraites":14956,"revenus_retraites":407543589},{"trancheName":"38 751 à 48 750","trancheMin":38751,"trancheMax":48750,"nbFoyers":17729,"nbFoyersImposables":17330,"revenus":764685406,"revenusImposables":747545970,"impot":45172125,"nbFoyers_salaires":12686,"revenus_salaires":523622951,"nbFoyers_retraites":6997,"revenus_retraites":226973605},{"trancheName":"48 751 à 97 500","trancheMin":48751,"trancheMax":97500,"nbFoyers":18542,"nbFoyersImposables":18242,"revenus":1169010821,"revenusImposables":1150509690,"impot":108307375,"nbFoyers_salaires":13239,"revenus_salaires":717307708,"nbFoyers_retraites":6640,"revenus_retraites":256184308},{"trancheName":"+ de 97 500","trancheMin":97500,"trancheMax":0,"nbFoyers":3946,"nbFoyersImposables":3901,"revenus":748598883,"revenusImposables":738873900,"impot":138960942,"nbFoyers_salaires":2808,"revenus_salaires":236059923,"nbFoyers_retraites":867,"revenus_retraites":35133508}],"nbFoyers":397177,"nbFoyersImposables":191721,"revenus":7816526461,"revenusImposables":6008891077,"impot":357600352,"nbFoyers_salaires":245323,"revenus_salaires":5132438710,"nbFoyers_retraites":144151,"revenus_retraites":2538467453},"2008":{"depNumber":"300","depName":"GARD","year":2008,"tranches":[{"trancheName":"0 à 9 400","trancheMin":0,"trancheMax":9400,"nbFoyers":118710,"nbFoyersImposables":211,"revenus":523070496,"revenusImposables":998807,"impot":-16491084,"nbFoyers_salaires":54749,"revenus_salaires":353600370,"nbFoyers_retraites":39425,"revenus_retraites":310378514},{"trancheName":"9 401 à 11 250","trancheMin":9401,"trancheMax":11250,"nbFoyers":27874,"nbFoyersImposables":564,"revenus":288072691,"revenusImposables":6238173,"impot":-8428716,"nbFoyers_salaires":18110,"revenus_salaires":214594939,"nbFoyers_retraites":10329,"revenus_retraites":125279011},{"trancheName":"11 251 à 13 150","trancheMin":11251,"trancheMax":13150,"nbFoyers":27633,"nbFoyersImposables":10581,"revenus":336767921,"revenusImposables":129891430,"impot":-8571625,"nbFoyers_salaires":20565,"revenus_salaires":286397967,"nbFoyers_retraites":7621,"revenus_retraites":100699834},{"trancheName":"13 151 à 15 000","trancheMin":13151,"trancheMax":15000,"nbFoyers":29710,"nbFoyersImposables":13433,"revenus":417869144,"revenusImposables":189597323,"impot":-2389178,"nbFoyers_salaires":19859,"revenus_salaires":311109891,"nbFoyers_retraites":10672,"revenus_retraites":162388498},{"trancheName":"15 001 à 16 900","trancheMin":15001,"trancheMax":16900,"nbFoyers":25805,"nbFoyersImposables":14023,"revenus":410702930,"revenusImposables":223106274,"impot":2148171,"nbFoyers_salaires":16908,"revenus_salaires":293729475,"nbFoyers_retraites":9944,"revenus_retraites":166530181},{"trancheName":"16 901 à 18 750","trancheMin":16901,"trancheMax":18750,"nbFoyers":20900,"nbFoyersImposables":13475,"revenus":371979939,"revenusImposables":240340888,"impot":2991663,"nbFoyers_salaires":13365,"revenus_salaires":253746594,"nbFoyers_retraites":8651,"revenus_retraites":158401968},{"trancheName":"18 751 à 23 750","trancheMin":18751,"trancheMax":23750,"nbFoyers":38909,"nbFoyersImposables":29650,"revenus":819127597,"revenusImposables":626614377,"impot":10897673,"nbFoyers_salaires":26833,"revenus_salaires":589297238,"nbFoyers_retraites":14935,"revenus_retraites":293587390},{"trancheName":"23 751 à 28 750","trancheMin":23751,"trancheMax":28750,"nbFoyers":31151,"nbFoyersImposables":27245,"revenus":813915205,"revenusImposables":712662752,"impot":15271965,"nbFoyers_salaires":20124,"revenus_salaires":533343029,"nbFoyers_retraites":13928,"revenus_retraites":325644633},{"trancheName":"28 751 à 38 750","trancheMin":28751,"trancheMax":38750,"nbFoyers":38410,"nbFoyersImposables":36366,"revenus":1275005111,"revenusImposables":1208935491,"impot":42645514,"nbFoyers_salaires":26402,"revenus_salaires":868578027,"nbFoyers_retraites":16249,"revenus_retraites":447007326},{"trancheName":"38 751 à 48 750","trancheMin":38751,"trancheMax":48750,"nbFoyers":19037,"nbFoyersImposables":18560,"revenus":821817773,"revenusImposables":801425597,"impot":43175940,"nbFoyers_salaires":13532,"revenus_salaires":562404739,"nbFoyers_retraites":7667,"revenus_retraites":249874189},{"trancheName":"48 751 à 97 500","trancheMin":48751,"trancheMax":97500,"nbFoyers":20482,"nbFoyersImposables":20100,"revenus":1292870554,"revenusImposables":1268764244,"impot":110614485,"nbFoyers_salaires":14673,"revenus_salaires":799291425,"nbFoyers_retraites":7544,"revenus_retraites":295261783},{"trancheName":"+ de 97 500","trancheMin":97500,"trancheMax":0,"nbFoyers":4152,"nbFoyersImposables":4091,"revenus":729964405,"revenusImposables":719635824,"impot":124100208,"nbFoyers_salaires":3000,"revenus_salaires":257131822,"nbFoyers_retraites":966,"revenus_retraites":39334902}],"nbFoyers":402773,"nbFoyersImposables":188299,"revenus":8101163766,"revenusImposables":6128211180,"impot":315965016,"nbFoyers_salaires":248120,"revenus_salaires":5323225516,"nbFoyers_retraites":147931,"revenus_retraites":2674388229},"2009":{"depNumber":"300","depName":"GARD","year":2009,"tranches":[{"trancheName":"0 à 9 400","trancheMin":0,"trancheMax":9400,"nbFoyers":119176,"nbFoyersImposables":198,"revenus":515883010,"revenusImposables":949252,"impot":-13707103,"nbFoyers_salaires":54260,"revenus_salaires":348324597,"nbFoyers_retraites":39008,"revenus_retraites":306543541},{"trancheName":"9 401 à 11 250","trancheMin":9401,"trancheMax":11250,"nbFoyers":27648,"nbFoyersImposables":315,"revenus":285610009,"revenusImposables":3485979,"impot":-7201638,"nbFoyers_salaires":17807,"revenus_salaires":210474252,"nbFoyers_retraites":10354,"revenus_retraites":125663604},{"trancheName":"11 251 à 13 150","trancheMin":11251,"trancheMax":13150,"nbFoyers":26750,"nbFoyersImposables":9908,"revenus":326122077,"revenusImposables":122083095,"impot":-7258876,"nbFoyers_salaires":19878,"revenus_salaires":277174692,"nbFoyers_retraites":7430,"revenus_retraites":98510983},{"trancheName":"13 151 à 15 000","trancheMin":13151,"trancheMax":15000,"nbFoyers":29672,"nbFoyersImposables":13131,"revenus":417704194,"revenusImposables":185452902,"impot":-1874331,"nbFoyers_salaires":19565,"revenus_salaires":307823336,"nbFoyers_retraites":10890,"revenus_retraites":167193594},{"trancheName":"15 001 à 16 900","trancheMin":15001,"trancheMax":16900,"nbFoyers":26079,"nbFoyersImposables":14388,"revenus":415173536,"revenusImposables":229073818,"impot":3198910,"nbFoyers_salaires":16977,"revenus_salaires":295075940,"nbFoyers_retraites":10117,"revenus_retraites":170607796},{"trancheName":"16 901 à 18 750","trancheMin":16901,"trancheMax":18750,"nbFoyers":21098,"nbFoyersImposables":13261,"revenus":375535107,"revenusImposables":236633969,"impot":3937268,"nbFoyers_salaires":13368,"revenus_salaires":254428071,"nbFoyers_retraites":8759,"revenus_retraites":161547727},{"trancheName":"18 751 à 23 750","trancheMin":18751,"trancheMax":23750,"nbFoyers":39676,"nbFoyersImposables":30328,"revenus":834694326,"revenusImposables":640287189,"impot":13969840,"nbFoyers_salaires":27195,"revenus_salaires":598172828,"nbFoyers_retraites":15369,"revenus_retraites":304649654},{"trancheName":"23 751 à 28 750","trancheMin":23751,"trancheMax":28750,"nbFoyers":31709,"nbFoyersImposables":27730,"revenus":828711444,"revenusImposables":725592820,"impot":18712515,"nbFoyers_salaires":20079,"revenus_salaires":530710455,"nbFoyers_retraites":14572,"revenus_retraites":345663862},{"trancheName":"28 751 à 38 750","trancheMin":28751,"trancheMax":38750,"nbFoyers":39628,"nbFoyersImposables":37444,"revenus":1314742190,"revenusImposables":1244151506,"impot":47599496,"nbFoyers_salaires":26980,"revenus_salaires":890233293,"nbFoyers_retraites":16935,"revenus_retraites":471881883},{"trancheName":"38 751 à 48 750","trancheMin":38751,"trancheMax":48750,"nbFoyers":20186,"nbFoyersImposables":19702,"revenus":871640930,"revenusImposables":850961922,"impot":45914023,"nbFoyers_salaires":14264,"revenus_salaires":596221028,"nbFoyers_retraites":8211,"revenus_retraites":273851555},{"trancheName":"48 751 à 97 500","trancheMin":48751,"trancheMax":97500,"nbFoyers":21785,"nbFoyersImposables":21368,"revenus":1373967323,"revenusImposables":1347691539,"impot":117307753,"nbFoyers_salaires":15635,"revenus_salaires":860485833,"nbFoyers_retraites":8106,"revenus_retraites":323975840},{"trancheName":"+ de 97 500","trancheMin":97500,"trancheMax":0,"nbFoyers":4092,"nbFoyersImposables":4020,"revenus":709144259,"revenusImposables":697750253,"impot":120081666,"nbFoyers_salaires":2946,"revenus_salaires":263711129,"nbFoyers_retraites":1006,"revenus_retraites":43802879}],"nbFoyers":407499,"nbFoyersImposables":191793,"revenus":8268928405,"revenusImposables":6284114244,"impot":340679523,"nbFoyers_salaires":248954,"revenus_salaires":5432835454,"nbFoyers_retraites":150757,"revenus_retraites":2793892918},"2010":{"depNumber":"300","depName":"GARD","year":2010,"tranches":[{"trancheName":"0 à 10 000","trancheMin":0,"trancheMax":10000,"nbFoyers":128086,"nbFoyersImposables":143,"revenus":598382223,"revenusImposables":749936,"impot":-13683579,"nbFoyers_salaires":59635,"revenus_salaires":409142962,"nbFoyers_retraites":42298,"revenus_retraites":348091063},{"trancheName":"10 001 à 12 000","trancheMin":10001,"trancheMax":12000,"nbFoyers":30121,"nbFoyersImposables":2261,"revenus":331587798,"revenusImposables":26387486,"impot":-7555425,"nbFoyers_salaires":20096,"revenus_salaires":252539246,"nbFoyers_retraites":10724,"revenus_retraites":136713461},{"trancheName":"12 001 à 15 000","trancheMin":12001,"trancheMax":15000,"nbFoyers":44035,"nbFoyersImposables":19005,"revenus":597311130,"revenusImposables":257950500,"impot":-5138638,"nbFoyers_salaires":31001,"revenus_salaires":473109008,"nbFoyers_retraites":14166,"revenus_retraites":209231723},{"trancheName":"15 001 à 20 000","trancheMin":15001,"trancheMax":20000,"nbFoyers":61237,"nbFoyersImposables":37096,"revenus":1059262251,"revenusImposables":646704798,"impot":11923408,"nbFoyers_salaires":39116,"revenus_salaires":730361590,"nbFoyers_retraites":24915,"revenus_retraites":450844204},{"trancheName":"20 001 à 30 000","trancheMin":20001,"trancheMax":30000,"nbFoyers":66764,"nbFoyersImposables":55653,"revenus":1644960010,"revenusImposables":1381865541,"impot":38043777,"nbFoyers_salaires":44218,"revenus_salaires":1113227383,"nbFoyers_retraites":28398,"revenus_retraites":643361803},{"trancheName":"30 001 à 50 000","trancheMin":30001,"trancheMax":50000,"nbFoyers":57319,"nbFoyersImposables":54824,"revenus":2169225792,"revenusImposables":2079891292,"impot":99493585,"nbFoyers_salaires":39596,"revenus_salaires":1473550508,"nbFoyers_retraites":24257,"revenus_retraites":739445299},{"trancheName":"50 001 à 100 000","trancheMin":50001,"trancheMax":100000,"nbFoyers":21865,"nbFoyersImposables":21365,"revenus":1412414879,"revenusImposables":1380197623,"impot":123139014,"nbFoyers_salaires":15685,"revenus_salaires":881251468,"nbFoyers_retraites":8303,"revenus_retraites":336019359},{"trancheName":"+ de 100 000","trancheMin":100000,"trancheMax":0,"nbFoyers":4261,"nbFoyersImposables":4181,"revenus":778506655,"revenusImposables":758513163,"impot":131687188,"nbFoyers_salaires":3054,"revenus_salaires":286881607,"nbFoyers_retraites":1116,"revenus_retraites":46916999}],"nbFoyers":413688,"nbFoyersImposables":194528,"revenus":8591650738,"revenusImposables":6532260339,"impot":377909330,"nbFoyers_salaires":252401,"revenus_salaires":5620063772,"nbFoyers_retraites":154177,"revenus_retraites":2910623911},"2011":{"depNumber":"300","depName":"GARD","year":2011,"tranches":[{"trancheName":"0 à 10 000","trancheMin":0,"trancheMax":10000,"nbFoyers":119041,"nbFoyersImposables":145,"revenus":551672074,"revenusImposables":760767,"impot":-11457444,"nbFoyers_salaires":52767,"revenus_salaires":359361739,"nbFoyers_retraites":40674,"revenus_retraites":337519002},{"trancheName":"10 001 à 12 000","trancheMin":10001,"trancheMax":12000,"nbFoyers":28706,"nbFoyersImposables":2197,"revenus":316082143,"revenusImposables":25647052,"impot":-6519377,"nbFoyers_salaires":18708,"revenus_salaires":237079637,"nbFoyers_retraites":10647,"revenus_retraites":135897843},{"trancheName":"12 001 à 15 000","trancheMin":12001,"trancheMax":15000,"nbFoyers":43272,"nbFoyersImposables":19562,"revenus":587659079,"revenusImposables":266061764,"impot":-3544782,"nbFoyers_salaires":30173,"revenus_salaires":462820403,"nbFoyers_retraites":14145,"revenus_retraites":209293560},{"trancheName":"15 001 à 20 000","trancheMin":15001,"trancheMax":20000,"nbFoyers":61896,"nbFoyersImposables":38614,"revenus":1071147762,"revenusImposables":673222404,"impot":16951173,"nbFoyers_salaires":39232,"revenus_salaires":734200959,"nbFoyers_retraites":25592,"revenus_retraites":465821121},{"trancheName":"20 001 à 30 000","trancheMin":20001,"trancheMax":30000,"nbFoyers":68279,"nbFoyersImposables":57209,"revenus":1683712170,"revenusImposables":1421244745,"impot":46437266,"nbFoyers_salaires":44826,"revenus_salaires":1132226512,"nbFoyers_retraites":29261,"revenus_retraites":668694815},{"trancheName":"30 001 à 50 000","trancheMin":30001,"trancheMax":50000,"nbFoyers":60685,"nbFoyersImposables":58035,"revenus":2302334214,"revenusImposables":2206523861,"impot":114035096,"nbFoyers_salaires":41537,"revenus_salaires":1554839079,"nbFoyers_retraites":25995,"revenus_retraites":800612999},{"trancheName":"50 001 à 100 000","trancheMin":50001,"trancheMax":100000,"nbFoyers":23805,"nbFoyersImposables":23204,"revenus":1539869344,"revenusImposables":1501491290,"impot":135692320,"nbFoyers_salaires":17056,"revenus_salaires":965284608,"nbFoyers_retraites":9106,"revenus_retraites":374231890},{"trancheName":"+ de 100 000","trancheMin":100000,"trancheMax":0,"nbFoyers":4597,"nbFoyersImposables":4526,"revenus":838942803,"revenusImposables":828200853,"impot":146334482,"nbFoyers_salaires":3373,"revenus_salaires":312861248,"nbFoyers_retraites":1264,"revenus_retraites":56593304}],"nbFoyers":410281,"nbFoyersImposables":203492,"revenus":8891419589,"revenusImposables":6923152736,"impot":437928734,"nbFoyers_salaires":247672,"revenus_salaires":5758674185,"nbFoyers_retraites":156684,"revenus_retraites":3048664534},"2012":{"depNumber":"300","depName":"GARD","year":2012,"tranches":[{"trancheName":"0 à 10 000","trancheMin":0,"trancheMax":10000,"nbFoyers":117269,"nbFoyersImposables":68,"revenus":534324258,"revenusImposables":390184,"impot":-9926771,"nbFoyers_salaires":50845,"revenus_salaires":343509822,"nbFoyers_retraites":39318,"revenus_retraites":326788213},{"trancheName":"10 001 à 12 000","trancheMin":10001,"trancheMax":12000,"nbFoyers":28261,"nbFoyersImposables":575,"revenus":311312329,"revenusImposables":6808334,"impot":-5506113,"nbFoyers_salaires":18030,"revenus_salaires":228291250,"nbFoyers_retraites":10739,"revenus_retraites":138891446},{"trancheName":"12 001 à 15 000","trancheMin":12001,"trancheMax":15000,"nbFoyers":42733,"nbFoyersImposables":21921,"revenus":579887035,"revenusImposables":299966531,"impot":-1556639,"nbFoyers_salaires":30184,"revenus_salaires":464019205,"nbFoyers_retraites":13615,"revenus_retraites":201150915},{"trancheName":"15 001 à 20 000","trancheMin":15001,"trancheMax":20000,"nbFoyers":63488,"nbFoyersImposables":39658,"revenus":1099650180,"revenusImposables":691168983,"impot":21824885,"nbFoyers_salaires":40508,"revenus_salaires":759642951,"nbFoyers_retraites":25776,"revenus_retraites":471990260},{"trancheName":"20 001 à 30 000","trancheMin":20001,"trancheMax":30000,"nbFoyers":68978,"nbFoyersImposables":57774,"revenus":1700010975,"revenusImposables":1434927145,"impot":52614381,"nbFoyers_salaires":44852,"revenus_salaires":1132847077,"nbFoyers_retraites":29845,"revenus_retraites":687128548},{"trancheName":"30 001 à 50 000","trancheMin":30001,"trancheMax":50000,"nbFoyers":62803,"nbFoyersImposables":60106,"revenus":2384015505,"revenusImposables":2286507292,"impot":124525237,"nbFoyers_salaires":42544,"revenus_salaires":1591600277,"nbFoyers_retraites":27357,"revenus_retraites":851885572},{"trancheName":"50 001 à 100 000","trancheMin":50001,"trancheMax":100000,"nbFoyers":25766,"nbFoyersImposables":25117,"revenus":1667033898,"revenusImposables":1625809220,"impot":151039191,"nbFoyers_salaires":18263,"revenus_salaires":1025397304,"nbFoyers_retraites":10211,"revenus_retraites":429101224},{"trancheName":"+ de 100 000","trancheMin":100000,"trancheMax":0,"nbFoyers":4957,"nbFoyersImposables":4866,"revenus":874570171,"revenusImposables":861009354,"impot":155197997,"nbFoyers_salaires":3651,"revenus_salaires":341260051,"nbFoyers_retraites":1423,"revenus_retraites":65746106}],"nbFoyers":414255,"nbFoyersImposables":210085,"revenus":9150804351,"revenusImposables":7206587043,"impot":488212168,"nbFoyers_salaires":248877,"revenus_salaires":5886567937,"nbFoyers_retraites":158284,"revenus_retraites":3172682284}}}