{"Gini":{"2003":0.4649935262,"2004":0.4663250778,"2005":0.4603929196,"2006":0.4562013531,"2007":0.4546724664,"2008":0.4565341071,"2009":0.4512312134,"2010":0.4480231972,"2011":0.4458434401,"2012":0.4501948088},"Lorenz":{"LorenzTranches":{"2003":[{"Key":0.0,"Value":0.0},{"Key":0.31528,"Value":0.07888},{"Key":0.39509,"Value":0.12095},{"Key":0.47765,"Value":0.17250},{"Key":0.54604,"Value":0.22160},{"Key":0.60296,"Value":0.26797},{"Key":0.65040,"Value":0.31111},{"Key":0.74330,"Value":0.41206},{"Key":0.81728,"Value":0.51096},{"Key":0.90317,"Value":0.65673},{"Key":0.94438,"Value":0.74778},{"Key":0.98971,"Value":0.89581},{"Key":1.00001,"Value":1.00001}],"2004":[{"Key":0.0,"Value":0.0},{"Key":0.30324,"Value":0.07302},{"Key":0.38109,"Value":0.11300},{"Key":0.46090,"Value":0.16155},{"Key":0.53230,"Value":0.21143},{"Key":0.59083,"Value":0.25784},{"Key":0.63988,"Value":0.30130},{"Key":0.73327,"Value":0.40003},{"Key":0.80901,"Value":0.49858},{"Key":0.89848,"Value":0.64618},{"Key":0.94203,"Value":0.73983},{"Key":0.98913,"Value":0.88909},{"Key":1.00001,"Value":1.00001}],"2005":[{"Key":0.0,"Value":0.0},{"Key":0.28706,"Value":0.06731},{"Key":0.36104,"Value":0.10450},{"Key":0.43983,"Value":0.15144},{"Key":0.51491,"Value":0.20273},{"Key":0.57676,"Value":0.25068},{"Key":0.62748,"Value":0.29463},{"Key":0.72242,"Value":0.39261},{"Key":0.79952,"Value":0.49078},{"Key":0.89317,"Value":0.64195},{"Key":0.93903,"Value":0.73841},{"Key":0.98893,"Value":0.89292},{"Key":1.00001,"Value":1.00001}],"2006":[{"Key":0.0,"Value":0.0},{"Key":0.27406,"Value":0.06226},{"Key":0.34433,"Value":0.09674},{"Key":0.42011,"Value":0.14083},{"Key":0.49698,"Value":0.19208},{"Key":0.56030,"Value":0.23992},{"Key":0.61232,"Value":0.28384},{"Key":0.70837,"Value":0.38022},{"Key":0.78724,"Value":0.47798},{"Key":0.88555,"Value":0.63271},{"Key":0.93403,"Value":0.73206},{"Key":0.98824,"Value":0.89555},{"Key":1.00001,"Value":1.00001}],"2007":[{"Key":0.0,"Value":0.0},{"Key":0.25901,"Value":0.05660},{"Key":0.32697,"Value":0.08888},{"Key":0.39977,"Value":0.12983},{"Key":0.47766,"Value":0.18009},{"Key":0.54346,"Value":0.22817},{"Key":0.59681,"Value":0.27176},{"Key":0.69571,"Value":0.36764},{"Key":0.77502,"Value":0.46277},{"Key":0.87658,"Value":0.61752},{"Key":0.92838,"Value":0.72023},{"Key":0.98688,"Value":0.89089},{"Key":1.00001,"Value":1.00001}],"2008":[{"Key":0.0,"Value":0.0},{"Key":0.24901,"Value":0.05193},{"Key":0.31314,"Value":0.08140},{"Key":0.38064,"Value":0.11803},{"Key":0.45874,"Value":0.16686},{"Key":0.52633,"Value":0.21468},{"Key":0.58129,"Value":0.25815},{"Key":0.68243,"Value":0.35272},{"Key":0.76308,"Value":0.44636},{"Key":0.86872,"Value":0.60225},{"Key":0.92396,"Value":0.70830},{"Key":0.98670,"Value":0.88560},{"Key":1.00001,"Value":1.00001}],"2009":[{"Key":0.0,"Value":0.0},{"Key":0.24626,"Value":0.05011},{"Key":0.30852,"Value":0.07872},{"Key":0.37371,"Value":0.11408},{"Key":0.44936,"Value":0.16137},{"Key":0.51777,"Value":0.20974},{"Key":0.57363,"Value":0.25393},{"Key":0.67524,"Value":0.34890},{"Key":0.75630,"Value":0.44297},{"Key":0.86392,"Value":0.60187},{"Key":0.92148,"Value":0.71234},{"Key":0.98664,"Value":0.89638},{"Key":1.00001,"Value":1.00001}],"2010":[{"Key":0.0,"Value":0.0},{"Key":0.25898,"Value":0.05562},{"Key":0.32727,"Value":0.08820},{"Key":0.43768,"Value":0.15317},{"Key":0.59562,"Value":0.27155},{"Key":0.76550,"Value":0.45291},{"Key":0.92212,"Value":0.71053},{"Key":0.98663,"Value":0.89248},{"Key":1.00001,"Value":1.00001}],"2011":[{"Key":0.0,"Value":0.0},{"Key":0.23679,"Value":0.04783},{"Key":0.30143,"Value":0.07706},{"Key":0.40869,"Value":0.13698},{"Key":0.56983,"Value":0.25156},{"Key":0.74502,"Value":0.42899},{"Key":0.91314,"Value":0.69180},{"Key":0.98483,"Value":0.88365},{"Key":1.00001,"Value":1.00001}],"2012":[{"Key":0.0,"Value":0.0},{"Key":0.23107,"Value":0.04497},{"Key":0.29340,"Value":0.07236},{"Key":0.39657,"Value":0.12831},{"Key":0.55910,"Value":0.24057},{"Key":0.73565,"Value":0.41398},{"Key":0.90693,"Value":0.67437},{"Key":0.98355,"Value":0.87387},{"Key":1.00001,"Value":1.00001}]},"LorenzDeciles":{"2003":[{"Key":0.0,"Value":0.0},{"Key":0.05,"Value":0.0125},{"Key":0.10,"Value":0.0250},{"Key":0.15,"Value":0.0375},{"Key":0.20,"Value":0.0500},{"Key":0.25,"Value":0.0625},{"Key":0.30,"Value":0.0751},{"Key":0.35,"Value":0.0972},{"Key":0.40,"Value":0.1240},{"Key":0.45,"Value":0.1552},{"Key":0.50,"Value":0.1885},{"Key":0.55,"Value":0.2248},{"Key":0.60,"Value":0.2656},{"Key":0.65,"Value":0.3107},{"Key":0.70,"Value":0.3650},{"Key":0.75,"Value":0.4210},{"Key":0.80,"Value":0.4879},{"Key":0.85,"Value":0.5665},{"Key":0.90,"Value":0.6513},{"Key":0.95,"Value":0.7661},{"Key":1.00,"Value":0.9999}],"2004":[{"Key":0.0,"Value":0.0},{"Key":0.05,"Value":0.0120},{"Key":0.10,"Value":0.0241},{"Key":0.15,"Value":0.0361},{"Key":0.20,"Value":0.0482},{"Key":0.25,"Value":0.0602},{"Key":0.30,"Value":0.0722},{"Key":0.35,"Value":0.0970},{"Key":0.40,"Value":0.1245},{"Key":0.45,"Value":0.1549},{"Key":0.50,"Value":0.1889},{"Key":0.55,"Value":0.2255},{"Key":0.60,"Value":0.2660},{"Key":0.65,"Value":0.3120},{"Key":0.70,"Value":0.3649},{"Key":0.75,"Value":0.4218},{"Key":0.80,"Value":0.4869},{"Key":0.85,"Value":0.5662},{"Key":0.90,"Value":0.6494},{"Key":0.95,"Value":0.7651},{"Key":1.00,"Value":0.9999}],"2005":[{"Key":0.0,"Value":0.0},{"Key":0.05,"Value":0.0117},{"Key":0.10,"Value":0.0234},{"Key":0.15,"Value":0.0352},{"Key":0.20,"Value":0.0469},{"Key":0.25,"Value":0.0586},{"Key":0.30,"Value":0.0738},{"Key":0.35,"Value":0.0990},{"Key":0.40,"Value":0.1277},{"Key":0.45,"Value":0.1584},{"Key":0.50,"Value":0.1925},{"Key":0.55,"Value":0.2299},{"Key":0.60,"Value":0.2708},{"Key":0.65,"Value":0.3179},{"Key":0.70,"Value":0.3695},{"Key":0.75,"Value":0.4277},{"Key":0.80,"Value":0.4916},{"Key":0.85,"Value":0.5723},{"Key":0.90,"Value":0.6563},{"Key":0.95,"Value":0.7724},{"Key":1.00,"Value":0.9999}],"2006":[{"Key":0.0,"Value":0.0},{"Key":0.05,"Value":0.0114},{"Key":0.10,"Value":0.0227},{"Key":0.15,"Value":0.0341},{"Key":0.20,"Value":0.0454},{"Key":0.25,"Value":0.0568},{"Key":0.30,"Value":0.0750},{"Key":0.35,"Value":0.1000},{"Key":0.40,"Value":0.1291},{"Key":0.45,"Value":0.1608},{"Key":0.50,"Value":0.1944},{"Key":0.55,"Value":0.2321},{"Key":0.60,"Value":0.2734},{"Key":0.65,"Value":0.3216},{"Key":0.70,"Value":0.3718},{"Key":0.75,"Value":0.4318},{"Key":0.80,"Value":0.4981},{"Key":0.85,"Value":0.5768},{"Key":0.90,"Value":0.6623},{"Key":0.95,"Value":0.7802},{"Key":1.00,"Value":0.9999}],"2007":[{"Key":0.0,"Value":0.0},{"Key":0.05,"Value":0.0109},{"Key":0.10,"Value":0.0219},{"Key":0.15,"Value":0.0328},{"Key":0.20,"Value":0.0437},{"Key":0.25,"Value":0.0546},{"Key":0.30,"Value":0.0761},{"Key":0.35,"Value":0.1018},{"Key":0.40,"Value":0.1300},{"Key":0.45,"Value":0.1622},{"Key":0.50,"Value":0.1964},{"Key":0.55,"Value":0.2335},{"Key":0.60,"Value":0.2749},{"Key":0.65,"Value":0.3233},{"Key":0.70,"Value":0.3728},{"Key":0.75,"Value":0.4328},{"Key":0.80,"Value":0.5008},{"Key":0.85,"Value":0.5770},{"Key":0.90,"Value":0.6640},{"Key":0.95,"Value":0.7833},{"Key":1.00,"Value":0.9999}],"2008":[{"Key":0.0,"Value":0.0},{"Key":0.05,"Value":0.0104},{"Key":0.10,"Value":0.0209},{"Key":0.15,"Value":0.0313},{"Key":0.20,"Value":0.0417},{"Key":0.25,"Value":0.0524},{"Key":0.30,"Value":0.0754},{"Key":0.35,"Value":0.1014},{"Key":0.40,"Value":0.1301},{"Key":0.45,"Value":0.1614},{"Key":0.50,"Value":0.1961},{"Key":0.55,"Value":0.2334},{"Key":0.60,"Value":0.2756},{"Key":0.65,"Value":0.3224},{"Key":0.70,"Value":0.3731},{"Key":0.75,"Value":0.4312},{"Key":0.80,"Value":0.5008},{"Key":0.85,"Value":0.5746},{"Key":0.90,"Value":0.6623},{"Key":0.95,"Value":0.7819},{"Key":1.00,"Value":0.9999}],"2009":[{"Key":0.0,"Value":0.0},{"Key":0.05,"Value":0.0102},{"Key":0.10,"Value":0.0203},{"Key":0.15,"Value":0.0305},{"Key":0.20,"Value":0.0407},{"Key":0.25,"Value":0.0518},{"Key":0.30,"Value":0.0748},{"Key":0.35,"Value":0.1012},{"Key":0.40,"Value":0.1305},{"Key":0.45,"Value":0.1618},{"Key":0.50,"Value":0.1972},{"Key":0.55,"Value":0.2352},{"Key":0.60,"Value":0.2786},{"Key":0.65,"Value":0.3253},{"Key":0.70,"Value":0.3776},{"Key":0.75,"Value":0.4357},{"Key":0.80,"Value":0.5075},{"Key":0.85,"Value":0.5813},{"Key":0.90,"Value":0.6711},{"Key":0.95,"Value":0.7929},{"Key":1.00,"Value":0.9999}],"2010":[{"Key":0.0,"Value":0.0},{"Key":0.05,"Value":0.0107},{"Key":0.10,"Value":0.0215},{"Key":0.15,"Value":0.0322},{"Key":0.20,"Value":0.0430},{"Key":0.25,"Value":0.0537},{"Key":0.30,"Value":0.0752},{"Key":0.35,"Value":0.1016},{"Key":0.40,"Value":0.1310},{"Key":0.45,"Value":0.1624},{"Key":0.50,"Value":0.1999},{"Key":0.55,"Value":0.2374},{"Key":0.60,"Value":0.2762},{"Key":0.65,"Value":0.3296},{"Key":0.70,"Value":0.3830},{"Key":0.75,"Value":0.4364},{"Key":0.80,"Value":0.5097},{"Key":0.85,"Value":0.5919},{"Key":0.90,"Value":0.6741},{"Key":0.95,"Value":0.7892},{"Key":1.00,"Value":0.9999}],"2011":[{"Key":0.0,"Value":0.0},{"Key":0.05,"Value":0.0101},{"Key":0.10,"Value":0.0202},{"Key":0.15,"Value":0.0303},{"Key":0.20,"Value":0.0404},{"Key":0.25,"Value":0.0538},{"Key":0.30,"Value":0.0764},{"Key":0.35,"Value":0.1042},{"Key":0.40,"Value":0.1321},{"Key":0.45,"Value":0.1664},{"Key":0.50,"Value":0.2019},{"Key":0.55,"Value":0.2375},{"Key":0.60,"Value":0.2821},{"Key":0.65,"Value":0.3328},{"Key":0.70,"Value":0.3834},{"Key":0.75,"Value":0.4368},{"Key":0.80,"Value":0.5149},{"Key":0.85,"Value":0.5931},{"Key":0.90,"Value":0.6713},{"Key":0.95,"Value":0.7904},{"Key":1.00,"Value":0.9999}],"2012":[{"Key":0.0,"Value":0.0},{"Key":0.05,"Value":0.0097},{"Key":0.10,"Value":0.0195},{"Key":0.15,"Value":0.0292},{"Key":0.20,"Value":0.0389},{"Key":0.25,"Value":0.0533},{"Key":0.30,"Value":0.0759},{"Key":0.35,"Value":0.1031},{"Key":0.40,"Value":0.1307},{"Key":0.45,"Value":0.1652},{"Key":0.50,"Value":0.1997},{"Key":0.55,"Value":0.2343},{"Key":0.60,"Value":0.2807},{"Key":0.65,"Value":0.3299},{"Key":0.70,"Value":0.3790},{"Key":0.75,"Value":0.4358},{"Key":0.80,"Value":0.5118},{"Key":0.85,"Value":0.5878},{"Key":0.90,"Value":0.6638},{"Key":0.95,"Value":0.7865},{"Key":1.00,"Value":0.9999}]}},"Moyennes":{"2003":15629.0,"2004":16060.0,"2005":16423.0,"2006":21077.0,"2007":21784.0,"2008":22505.0,"2009":22507.0,"2010":23089.0,"2011":24355.0,"2012":25084.0},"Numero":"640","Nom":"PYRENEES-ATLANTIQUES","Data":{"2003":{"depNumber":"640","depName":"PYRENEES-ATLANTIQUES","year":2003,"tranches":[{"trancheName":"0 à 7 500","trancheMin":0,"trancheMax":7500,"nbFoyers":112265,"nbFoyersImposables":1846,"revenus":439011832,"revenusImposables":8094184,"impot":-8110029,"nbFoyers_salaires":51102,"revenus_salaires":351889709,"nbFoyers_retraites":44371,"revenus_retraites":344957109},{"trancheName":"7 501 à 9 000","trancheMin":7501,"trancheMax":9000,"nbFoyers":28417,"nbFoyersImposables":8665,"revenus":234110330,"revenusImposables":74147018,"impot":-4565634,"nbFoyers_salaires":20743,"revenus_salaires":246371545,"nbFoyers_retraites":7718,"revenus_retraites":89867747},{"trancheName":"9 001 à 10 500","trancheMin":9001,"trancheMax":10500,"nbFoyers":29396,"nbFoyersImposables":14991,"revenus":286886586,"revenusImposables":146111563,"impot":1723277,"nbFoyers_salaires":20677,"revenus_salaires":282591537,"nbFoyers_retraites":9040,"revenus_retraites":119765058},{"trancheName":"10 501 à 12 000","trancheMin":10501,"trancheMax":12000,"nbFoyers":24352,"nbFoyersImposables":13576,"revenus":273230254,"revenusImposables":152497888,"impot":6292918,"nbFoyers_salaires":16361,"revenus_salaires":252065023,"nbFoyers_retraites":8531,"revenus_retraites":125572968},{"trancheName":"12 001 à 13500","trancheMin":12001,"trancheMax":13500,"nbFoyers":20267,"nbFoyersImposables":12756,"revenus":258045747,"revenusImposables":162828877,"impot":7317061,"nbFoyers_salaires":13175,"revenus_salaires":225567692,"nbFoyers_retraites":7713,"revenus_retraites":126194623},{"trancheName":"13501 à 15 000","trancheMin":13501,"trancheMax":15000,"nbFoyers":16894,"nbFoyersImposables":12354,"revenus":240110387,"revenusImposables":175734424,"impot":8217596,"nbFoyers_salaires":11156,"revenus_salaires":210620446,"nbFoyers_retraites":6387,"revenus_retraites":112467199},{"trancheName":"15 001 à 19 000","trancheMin":15001,"trancheMax":19000,"nbFoyers":33081,"nbFoyersImposables":27294,"revenus":561809945,"revenusImposables":465010617,"impot":23134249,"nbFoyers_salaires":23164,"revenus_salaires":514978937,"nbFoyers_retraites":11396,"revenus_retraites":223804253},{"trancheName":"19 001 à 23 000","trancheMin":19001,"trancheMax":23000,"nbFoyers":26341,"nbFoyersImposables":23857,"revenus":550388766,"revenusImposables":499124943,"impot":28320571,"nbFoyers_salaires":17736,"revenus_salaires":475720425,"nbFoyers_retraites":10017,"revenus_retraites":233985834},{"trancheName":"23 001 à 31 000","trancheMin":23001,"trancheMax":31000,"nbFoyers":30584,"nbFoyersImposables":29297,"revenus":811240607,"revenusImposables":777892440,"impot":56128284,"nbFoyers_salaires":21186,"revenus_salaires":698379834,"nbFoyers_retraites":11252,"revenus_retraites":312142782},{"trancheName":"31 001 à 39 000","trancheMin":31001,"trancheMax":39000,"nbFoyers":14674,"nbFoyersImposables":14345,"revenus":506701068,"revenusImposables":495386162,"impot":47489594,"nbFoyers_salaires":10251,"revenus_salaires":419386443,"nbFoyers_retraites":5328,"revenus_retraites":177241442},{"trancheName":"39 001 à 78 000","trancheMin":39001,"trancheMax":78000,"nbFoyers":16142,"nbFoyersImposables":15893,"revenus":823811049,"revenusImposables":811684895,"impot":109284989,"nbFoyers_salaires":11016,"revenus_salaires":569671073,"nbFoyers_retraites":5469,"revenus_retraites":226286487},{"trancheName":"+ de 78 000","trancheMin":78000,"trancheMax":0,"nbFoyers":3663,"nbFoyersImposables":3646,"revenus":579986150,"revenusImposables":578355213,"impot":119522617,"nbFoyers_salaires":2531,"revenus_salaires":171653310,"nbFoyers_retraites":783,"revenus_retraites":32435662}],"nbFoyers":356076,"nbFoyersImposables":178520,"revenus":5565332721,"revenusImposables":4346868224,"impot":394755493,"nbFoyers_salaires":219098,"revenus_salaires":4418895974,"nbFoyers_retraites":128005,"revenus_retraites":2124721164},"2004":{"depNumber":"640","depName":"PYRENEES ATLANTIQUES","year":2004,"tranches":[{"trancheName":"0 à 7 500","trancheMin":0,"trancheMax":7500,"nbFoyers":109213,"nbFoyersImposables":1757,"revenus":422372818,"revenusImposables":7566912,"impot":-7870703,"nbFoyers_salaires":49042,"revenus_salaires":335886002,"nbFoyers_retraites":42817,"revenus_retraites":338314547},{"trancheName":"7 501 à 9 000","trancheMin":7501,"trancheMax":9000,"nbFoyers":28039,"nbFoyersImposables":6720,"revenus":231265192,"revenusImposables":57965924,"impot":-4961730,"nbFoyers_salaires":19898,"revenus_salaires":237823715,"nbFoyers_retraites":8206,"revenus_retraites":96931966},{"trancheName":"9 001 à 10 500","trancheMin":9001,"trancheMax":10500,"nbFoyers":28744,"nbFoyersImposables":15104,"revenus":280802367,"revenusImposables":147083668,"impot":433485,"nbFoyers_salaires":20719,"revenus_salaires":284427976,"nbFoyers_retraites":8330,"revenus_retraites":111267716},{"trancheName":"10 501 à 12 000","trancheMin":10501,"trancheMax":12000,"nbFoyers":25716,"nbFoyersImposables":14379,"revenus":288547199,"revenusImposables":161627969,"impot":6099182,"nbFoyers_salaires":17388,"revenus_salaires":269155484,"nbFoyers_retraites":8863,"revenus_retraites":131403487},{"trancheName":"12 001 à 13500","trancheMin":12001,"trancheMax":13500,"nbFoyers":21079,"nbFoyersImposables":13077,"revenus":268456757,"revenusImposables":166901581,"impot":7665304,"nbFoyers_salaires":13875,"revenus_salaires":238216598,"nbFoyers_retraites":7899,"revenus_retraites":129501870},{"trancheName":"13501 à 15 000","trancheMin":13501,"trancheMax":15000,"nbFoyers":17664,"nbFoyersImposables":12962,"revenus":251410812,"revenusImposables":184568376,"impot":8488988,"nbFoyers_salaires":11452,"revenus_salaires":217241778,"nbFoyers_retraites":6927,"revenus_retraites":124477612},{"trancheName":"15 001 à 19 000","trancheMin":15001,"trancheMax":19000,"nbFoyers":33636,"nbFoyersImposables":27688,"revenus":571072281,"revenusImposables":471551389,"impot":23757823,"nbFoyers_salaires":23595,"revenus_salaires":523083162,"nbFoyers_retraites":11842,"revenus_retraites":231114922},{"trancheName":"19 001 à 23 000","trancheMin":19001,"trancheMax":23000,"nbFoyers":27277,"nbFoyersImposables":24707,"revenus":570033950,"revenusImposables":516731274,"impot":28825433,"nbFoyers_salaires":18171,"revenus_salaires":489436108,"nbFoyers_retraites":10677,"revenus_retraites":250735873},{"trancheName":"23 001 à 31 000","trancheMin":23001,"trancheMax":31000,"nbFoyers":32224,"nbFoyersImposables":30804,"revenus":853789557,"revenusImposables":817015705,"impot":58035788,"nbFoyers_salaires":22390,"revenus_salaires":737421034,"nbFoyers_retraites":12130,"revenus_retraites":335474383},{"trancheName":"31 001 à 39 000","trancheMin":31001,"trancheMax":39000,"nbFoyers":15684,"nbFoyersImposables":15308,"revenus":541678553,"revenusImposables":528757368,"impot":49761982,"nbFoyers_salaires":10855,"revenus_salaires":444319610,"nbFoyers_retraites":5914,"revenus_retraites":199280766},{"trancheName":"39 001 à 78 000","trancheMin":39001,"trancheMax":78000,"nbFoyers":16964,"nbFoyersImposables":16614,"revenus":863356258,"revenusImposables":845766276,"impot":112249507,"nbFoyers_salaires":11573,"revenus_salaires":608721431,"nbFoyers_retraites":5906,"revenus_retraites":250409676},{"trancheName":"+ de 78 000","trancheMin":78000,"trancheMax":0,"nbFoyers":3912,"nbFoyersImposables":3865,"revenus":641561423,"revenusImposables":636123042,"impot":130559979,"nbFoyers_salaires":2756,"revenus_salaires":198649208,"nbFoyers_retraites":833,"revenus_retraites":36670921}],"nbFoyers":360152,"nbFoyersImposables":182985,"revenus":5784347167,"revenusImposables":4541659484,"impot":413045038,"nbFoyers_salaires":221714,"revenus_salaires":4584382106,"nbFoyers_retraites":130344,"revenus_retraites":2235583739},"2005":{"depNumber":"640","depName":"PYRENEES ATLANTIQUES","year":2005,"tranches":[{"trancheName":"0 à 7 500","trancheMin":0,"trancheMax":7500,"nbFoyers":104289,"nbFoyersImposables":3424,"revenus":401613904,"revenusImposables":14267542,"impot":-8613435,"nbFoyers_salaires":46507,"revenus_salaires":311300993,"nbFoyers_retraites":41969,"revenus_retraites":337234578},{"trancheName":"7 501 à 9 000","trancheMin":7501,"trancheMax":9000,"nbFoyers":26877,"nbFoyersImposables":5182,"revenus":221872568,"revenusImposables":44718243,"impot":-5536426,"nbFoyers_salaires":18321,"revenus_salaires":217837528,"nbFoyers_retraites":8800,"revenus_retraites":104846341},{"trancheName":"9 001 à 10 500","trancheMin":9001,"trancheMax":10500,"nbFoyers":28623,"nbFoyersImposables":15655,"revenus":280063645,"revenusImposables":152577345,"impot":-1465326,"nbFoyers_salaires":21027,"revenus_salaires":288639264,"nbFoyers_retraites":8019,"revenus_retraites":107282083},{"trancheName":"10 501 à 12 000","trancheMin":10501,"trancheMax":12000,"nbFoyers":27276,"nbFoyersImposables":15778,"revenus":306033246,"revenusImposables":177408648,"impot":5468347,"nbFoyers_salaires":18663,"revenus_salaires":287529254,"nbFoyers_retraites":9403,"revenus_retraites":140602236},{"trancheName":"12 001 à 13500","trancheMin":12001,"trancheMax":13500,"nbFoyers":22470,"nbFoyersImposables":14183,"revenus":286121979,"revenusImposables":180758580,"impot":7894757,"nbFoyers_salaires":15187,"revenus_salaires":260281074,"nbFoyers_retraites":8179,"revenus_retraites":134245895},{"trancheName":"13501 à 15 000","trancheMin":13501,"trancheMax":15000,"nbFoyers":18428,"nbFoyersImposables":13621,"revenus":262253195,"revenusImposables":193881420,"impot":8552952,"nbFoyers_salaires":11956,"revenus_salaires":225505653,"nbFoyers_retraites":7356,"revenus_retraites":133268178},{"trancheName":"15 001 à 19 000","trancheMin":15001,"trancheMax":19000,"nbFoyers":34493,"nbFoyersImposables":28401,"revenus":584632331,"revenusImposables":482842552,"impot":23517419,"nbFoyers_salaires":24067,"revenus_salaires":527305355,"nbFoyers_retraites":12579,"revenus_retraites":245749982},{"trancheName":"19 001 à 23 000","trancheMin":19001,"trancheMax":23000,"nbFoyers":28012,"nbFoyersImposables":25451,"revenus":585770807,"revenusImposables":532619769,"impot":28304462,"nbFoyers_salaires":18544,"revenus_salaires":494557172,"nbFoyers_retraites":11524,"revenus_retraites":271161684},{"trancheName":"23 001 à 31 000","trancheMin":23001,"trancheMax":31000,"nbFoyers":34023,"nbFoyersImposables":32399,"revenus":902005678,"revenusImposables":859805667,"impot":58109694,"nbFoyers_salaires":23637,"revenus_salaires":775985327,"nbFoyers_retraites":13344,"revenus_retraites":367838848},{"trancheName":"31 001 à 39 000","trancheMin":31001,"trancheMax":39000,"nbFoyers":16661,"nbFoyersImposables":16228,"revenus":575557843,"revenusImposables":560700537,"impot":51580422,"nbFoyers_salaires":11601,"revenus_salaires":469378171,"nbFoyers_retraites":6516,"revenus_retraites":218749297},{"trancheName":"39 001 à 78 000","trancheMin":39001,"trancheMax":78000,"nbFoyers":18130,"nbFoyersImposables":17697,"revenus":921912026,"revenusImposables":899979950,"impot":119979967,"nbFoyers_salaires":12379,"revenus_salaires":656601086,"nbFoyers_retraites":6618,"revenus_retraites":281190453},{"trancheName":"+ de 78 000","trancheMin":78000,"trancheMax":0,"nbFoyers":4023,"nbFoyersImposables":3961,"revenus":638828391,"revenusImposables":631155994,"impot":140819629,"nbFoyers_salaires":2792,"revenus_salaires":215481191,"nbFoyers_retraites":932,"revenus_retraites":40461367}],"nbFoyers":363305,"nbFoyersImposables":191980,"revenus":5966665613,"revenusImposables":4730716247,"impot":428612462,"nbFoyers_salaires":224681,"revenus_salaires":4730402068,"nbFoyers_retraites":135239,"revenus_retraites":2382630942},"2006":{"depNumber":"640","depName":"PYRENEES-ATLANTIQUES","year":2006,"tranches":[{"trancheName":"0 à 9 400","trancheMin":0,"trancheMax":9400,"nbFoyers":101325,"nbFoyersImposables":1468,"revenus":485210386,"revenusImposables":7513838,"impot":-12799203,"nbFoyers_salaires":44398,"revenus_salaires":289966049,"nbFoyers_retraites":40750,"revenus_retraites":329729419},{"trancheName":"9 401 à 11 250","trancheMin":9401,"trancheMax":11250,"nbFoyers":25979,"nbFoyersImposables":3406,"revenus":268722599,"revenusImposables":37053469,"impot":-7792031,"nbFoyers_salaires":17034,"revenus_salaires":202159775,"nbFoyers_retraites":9188,"revenus_retraites":111389215},{"trancheName":"11 251 à 13 150","trancheMin":11251,"trancheMax":13150,"nbFoyers":28017,"nbFoyersImposables":15292,"revenus":343595565,"revenusImposables":187015700,"impot":-5869912,"nbFoyers_salaires":20945,"revenus_salaires":288830046,"nbFoyers_retraites":7530,"revenus_retraites":100582040},{"trancheName":"13 151 à 15 000","trancheMin":13151,"trancheMax":15000,"nbFoyers":28420,"nbFoyersImposables":16073,"revenus":399359648,"revenusImposables":226552363,"impot":1841395,"nbFoyers_salaires":19597,"revenus_salaires":302639355,"nbFoyers_retraites":9543,"revenus_retraites":144064550},{"trancheName":"15 001 à 16 900","trancheMin":15001,"trancheMax":16900,"nbFoyers":23409,"nbFoyersImposables":14526,"revenus":372785733,"revenusImposables":231432429,"impot":6352090,"nbFoyers_salaires":15865,"revenus_salaires":271120599,"nbFoyers_retraites":8464,"revenus_retraites":139285570},{"trancheName":"16 901 à 18 750","trancheMin":16901,"trancheMax":18750,"nbFoyers":19231,"nbFoyersImposables":13976,"revenus":342249153,"revenusImposables":248906319,"impot":7033972,"nbFoyers_salaires":12598,"revenus_salaires":235873364,"nbFoyers_retraites":7567,"revenus_retraites":137682007},{"trancheName":"18 751 à 23 750","trancheMin":18751,"trancheMax":23750,"nbFoyers":35512,"nbFoyersImposables":28675,"revenus":751049348,"revenusImposables":608373172,"impot":17901925,"nbFoyers_salaires":24827,"revenus_salaires":539264977,"nbFoyers_retraites":13102,"revenus_retraites":255697544},{"trancheName":"23 751 à 28 750","trancheMin":23751,"trancheMax":28750,"nbFoyers":29160,"nbFoyersImposables":25958,"revenus":761839833,"revenusImposables":678773691,"impot":21552270,"nbFoyers_salaires":19293,"revenus_salaires":506341471,"nbFoyers_retraites":12263,"revenus_retraites":288999618},{"trancheName":"28 751 à 38 750","trancheMin":28751,"trancheMax":38750,"nbFoyers":36347,"nbFoyersImposables":34183,"revenus":1205797444,"revenusImposables":1135518144,"impot":52034963,"nbFoyers_salaires":25257,"revenus_salaires":821768940,"nbFoyers_retraites":14534,"revenus_retraites":402666245},{"trancheName":"38 751 à 48 750","trancheMin":38751,"trancheMax":48750,"nbFoyers":17924,"nbFoyersImposables":17287,"revenus":774188499,"revenusImposables":746880135,"impot":46232825,"nbFoyers_salaires":12513,"revenus_salaires":506325566,"nbFoyers_retraites":7131,"revenus_retraites":240502120},{"trancheName":"48 751 à 97 500","trancheMin":48751,"trancheMax":97500,"nbFoyers":20042,"nbFoyersImposables":19476,"revenus":1274065210,"revenusImposables":1237947302,"impot":117709136,"nbFoyers_salaires":13922,"revenus_salaires":741170509,"nbFoyers_retraites":7400,"revenus_retraites":315216820},{"trancheName":"+ de 97 500","trancheMin":97500,"trancheMax":0,"nbFoyers":4352,"nbFoyersImposables":4278,"revenus":813958127,"revenusImposables":803228264,"impot":144397802,"nbFoyers_salaires":3082,"revenus_salaires":248992576,"nbFoyers_retraites":1072,"revenus_retraites":48582963}],"nbFoyers":369718,"nbFoyersImposables":194598,"revenus":7792821545,"revenusImposables":6149194826,"impot":388595232,"nbFoyers_salaires":229331,"revenus_salaires":4954453227,"nbFoyers_retraites":138544,"revenus_retraites":2514398111},"2007":{"depNumber":"640","depName":"PYRENEES-ATLANTIQUES","year":2007,"tranches":[{"trancheName":"0 à 9 400","trancheMin":0,"trancheMax":9400,"nbFoyers":96774,"nbFoyersImposables":1472,"revenus":460658072,"revenusImposables":7587053,"impot":-12254038,"nbFoyers_salaires":41886,"revenus_salaires":276942328,"nbFoyers_retraites":38691,"revenus_retraites":315349326},{"trancheName":"9 401 à 11 250","trancheMin":9401,"trancheMax":11250,"nbFoyers":25390,"nbFoyersImposables":2629,"revenus":262699997,"revenusImposables":28673063,"impot":-7256336,"nbFoyers_salaires":16212,"revenus_salaires":192351094,"nbFoyers_retraites":9434,"revenus_retraites":115316614},{"trancheName":"11 251 à 13 150","trancheMin":11251,"trancheMax":13150,"nbFoyers":27200,"nbFoyersImposables":14537,"revenus":333338026,"revenusImposables":177986889,"impot":-6294353,"nbFoyers_salaires":20325,"revenus_salaires":281544501,"nbFoyers_retraites":7259,"revenus_retraites":97893559},{"trancheName":"13 151 à 15 000","trancheMin":13151,"trancheMax":15000,"nbFoyers":29102,"nbFoyersImposables":16411,"revenus":409039190,"revenusImposables":231447944,"impot":1179429,"nbFoyers_salaires":20070,"revenus_salaires":311393626,"nbFoyers_retraites":9793,"revenus_retraites":147978129},{"trancheName":"15 001 à 16 900","trancheMin":15001,"trancheMax":16900,"nbFoyers":24583,"nbFoyersImposables":15575,"revenus":391311457,"revenusImposables":247976374,"impot":6555515,"nbFoyers_salaires":16780,"revenus_salaires":288596686,"nbFoyers_retraites":8709,"revenus_retraites":144507247},{"trancheName":"16 901 à 18 750","trancheMin":16901,"trancheMax":18750,"nbFoyers":19934,"nbFoyersImposables":14535,"revenus":354809855,"revenusImposables":259036784,"impot":7261370,"nbFoyers_salaires":13041,"revenus_salaires":245082722,"nbFoyers_retraites":7908,"revenus_retraites":144562160},{"trancheName":"18 751 à 23 750","trancheMin":18751,"trancheMax":23750,"nbFoyers":36952,"nbFoyersImposables":29851,"revenus":780351549,"revenusImposables":632350781,"impot":18944163,"nbFoyers_salaires":25735,"revenus_salaires":557948686,"nbFoyers_retraites":13780,"revenus_retraites":271550671},{"trancheName":"23 751 à 28 750","trancheMin":23751,"trancheMax":28750,"nbFoyers":29632,"nbFoyersImposables":26499,"revenus":774257077,"revenusImposables":692838884,"impot":21875544,"nbFoyers_salaires":19145,"revenus_salaires":501560085,"nbFoyers_retraites":12962,"revenus_retraites":306996382},{"trancheName":"28 751 à 38 750","trancheMin":28751,"trancheMax":38750,"nbFoyers":37947,"nbFoyersImposables":35874,"revenus":1259544041,"revenusImposables":1192342686,"impot":52368226,"nbFoyers_salaires":26125,"revenus_salaires":852288447,"nbFoyers_retraites":15507,"revenus_retraites":432094037},{"trancheName":"38 751 à 48 750","trancheMin":38751,"trancheMax":48750,"nbFoyers":19354,"nbFoyersImposables":18771,"revenus":835981534,"revenusImposables":810964280,"impot":48506081,"nbFoyers_salaires":13452,"revenus_salaires":549133304,"nbFoyers_retraites":7854,"revenus_retraites":264979435},{"trancheName":"48 751 à 97 500","trancheMin":48751,"trancheMax":97500,"nbFoyers":21856,"nbFoyersImposables":21315,"revenus":1389064540,"revenusImposables":1354055983,"impot":124004646,"nbFoyers_salaires":15012,"revenus_salaires":811674426,"nbFoyers_retraites":8315,"revenus_retraites":354153681},{"trancheName":"+ de 97 500","trancheMin":97500,"trancheMax":0,"nbFoyers":4900,"nbFoyersImposables":4817,"revenus":888159990,"revenusImposables":875077824,"impot":155070654,"nbFoyers_salaires":3464,"revenus_salaires":281525470,"nbFoyers_retraites":1241,"revenus_retraites":58940840}],"nbFoyers":373624,"nbFoyersImposables":202286,"revenus":8139215328,"revenusImposables":6510338545,"impot":409960901,"nbFoyers_salaires":231247,"revenus_salaires":5150041375,"nbFoyers_retraites":141453,"revenus_retraites":2654322081},"2008":{"depNumber":"640","depName":"PYRENEES-ATLANTIQUES","year":2008,"tranches":[{"trancheName":"0 à 9 400","trancheMin":0,"trancheMax":9400,"nbFoyers":94223,"nbFoyersImposables":185,"revenus":442263385,"revenusImposables":755920,"impot":-12805092,"nbFoyers_salaires":40463,"revenus_salaires":263104239,"nbFoyers_retraites":37075,"revenus_retraites":304598472},{"trancheName":"9 401 à 11 250","trancheMin":9401,"trancheMax":11250,"nbFoyers":24265,"nbFoyersImposables":513,"revenus":250959581,"revenusImposables":5690602,"impot":-6966034,"nbFoyers_salaires":15018,"revenus_salaires":176553441,"nbFoyers_retraites":9535,"revenus_retraites":116641227},{"trancheName":"11 251 à 13 150","trancheMin":11251,"trancheMax":13150,"nbFoyers":25542,"nbFoyersImposables":10945,"revenus":311897991,"revenusImposables":134669023,"impot":-7563188,"nbFoyers_salaires":18910,"revenus_salaires":261706088,"nbFoyers_retraites":7051,"revenus_retraites":94758147},{"trancheName":"13 151 à 15 000","trancheMin":13151,"trancheMax":15000,"nbFoyers":29554,"nbFoyersImposables":15171,"revenus":415834332,"revenusImposables":214168361,"impot":-1470533,"nbFoyers_salaires":20239,"revenus_salaires":314307937,"nbFoyers_retraites":10133,"revenus_retraites":153503541},{"trancheName":"15 001 à 16 900","trancheMin":15001,"trancheMax":16900,"nbFoyers":25576,"nbFoyersImposables":15653,"revenus":407213705,"revenusImposables":249147748,"impot":4146868,"nbFoyers_salaires":17591,"revenus_salaires":303166646,"nbFoyers_retraites":8876,"revenus_retraites":148057739},{"trancheName":"16 901 à 18 750","trancheMin":16901,"trancheMax":18750,"nbFoyers":20795,"nbFoyersImposables":14461,"revenus":370209520,"revenusImposables":257883889,"impot":5153198,"nbFoyers_salaires":13701,"revenus_salaires":257347740,"nbFoyers_retraites":8104,"revenus_retraites":148369825},{"trancheName":"18 751 à 23 750","trancheMin":18751,"trancheMax":23750,"nbFoyers":38270,"nbFoyersImposables":30044,"revenus":805317189,"revenusImposables":633952715,"impot":15225978,"nbFoyers_salaires":26653,"revenus_salaires":577150779,"nbFoyers_retraites":14274,"revenus_retraites":282420227},{"trancheName":"23 751 à 28 750","trancheMin":23751,"trancheMax":28750,"nbFoyers":30519,"nbFoyersImposables":26680,"revenus":797409855,"revenusImposables":697741353,"impot":17497426,"nbFoyers_salaires":19553,"revenus_salaires":507501055,"nbFoyers_retraites":13770,"revenus_retraites":325453607},{"trancheName":"28 751 à 38 750","trancheMin":28751,"trancheMax":38750,"nbFoyers":39975,"nbFoyersImposables":37438,"revenus":1327554363,"revenusImposables":1245117890,"impot":45496947,"nbFoyers_salaires":27425,"revenus_salaires":895935305,"nbFoyers_retraites":16646,"revenus_retraites":467292138},{"trancheName":"38 751 à 48 750","trancheMin":38751,"trancheMax":48750,"nbFoyers":20903,"nbFoyersImposables":20245,"revenus":903133940,"revenusImposables":874767994,"impot":46741135,"nbFoyers_salaires":14550,"revenus_salaires":597422117,"nbFoyers_retraites":8606,"revenus_retraites":292559731},{"trancheName":"48 751 à 97 500","trancheMin":48751,"trancheMax":97500,"nbFoyers":23742,"nbFoyersImposables":23113,"revenus":1509873294,"revenusImposables":1469364313,"impot":125636737,"nbFoyers_salaires":16426,"revenus_salaires":894362410,"nbFoyers_retraites":9241,"revenus_retraites":398588528},{"trancheName":"+ de 97 500","trancheMin":97500,"trancheMax":0,"nbFoyers":5029,"nbFoyersImposables":4911,"revenus":974163973,"revenusImposables":955509471,"impot":157938679,"nbFoyers_salaires":3606,"revenus_salaires":313107119,"nbFoyers_retraites":1296,"revenus_retraites":60729023}],"nbFoyers":378393,"nbFoyersImposables":199359,"revenus":8515831128,"revenusImposables":6738769279,"impot":389032121,"nbFoyers_salaires":234135,"revenus_salaires":5361664876,"nbFoyers_retraites":144607,"revenus_retraites":2792972205},"2009":{"depNumber":"640","depName":"PYRENEES-ATLANTIQUES","year":2009,"tranches":[{"trancheName":"0 à 9 400","trancheMin":0,"trancheMax":9400,"nbFoyers":93909,"nbFoyersImposables":161,"revenus":430139186,"revenusImposables":762948,"impot":-11371257,"nbFoyers_salaires":40195,"revenus_salaires":256273867,"nbFoyers_retraites":36082,"revenus_retraites":296138802},{"trancheName":"9 401 à 11 250","trancheMin":9401,"trancheMax":11250,"nbFoyers":23744,"nbFoyersImposables":308,"revenus":245545914,"revenusImposables":3403220,"impot":-5973588,"nbFoyers_salaires":14682,"revenus_salaires":172367547,"nbFoyers_retraites":9414,"revenus_retraites":115641435},{"trancheName":"11 251 à 13 150","trancheMin":11251,"trancheMax":13150,"nbFoyers":24859,"nbFoyersImposables":10170,"revenus":303471892,"revenusImposables":125436169,"impot":-6412881,"nbFoyers_salaires":18195,"revenus_salaires":251312869,"nbFoyers_retraites":7170,"revenus_retraites":96643078},{"trancheName":"13 151 à 15 000","trancheMin":13151,"trancheMax":15000,"nbFoyers":28847,"nbFoyersImposables":14576,"revenus":405867619,"revenusImposables":205535417,"impot":-914217,"nbFoyers_salaires":19505,"revenus_salaires":303535326,"nbFoyers_retraites":10099,"revenus_retraites":154022462},{"trancheName":"15 001 à 16 900","trancheMin":15001,"trancheMax":16900,"nbFoyers":26088,"nbFoyersImposables":15896,"revenus":415171992,"revenusImposables":253017214,"impot":4850367,"nbFoyers_salaires":17824,"revenus_salaires":308223276,"nbFoyers_retraites":9077,"revenus_retraites":153234215},{"trancheName":"16 901 à 18 750","trancheMin":16901,"trancheMax":18750,"nbFoyers":21303,"nbFoyersImposables":14517,"revenus":379253790,"revenusImposables":258895123,"impot":6078692,"nbFoyers_salaires":13970,"revenus_salaires":263099870,"nbFoyers_retraites":8330,"revenus_retraites":154058028},{"trancheName":"18 751 à 23 750","trancheMin":18751,"trancheMax":23750,"nbFoyers":38750,"nbFoyersImposables":30502,"revenus":815143847,"revenusImposables":643673091,"impot":17887996,"nbFoyers_salaires":26768,"revenus_salaires":580632647,"nbFoyers_retraites":14576,"revenus_retraites":292963555},{"trancheName":"23 751 à 28 750","trancheMin":23751,"trancheMax":28750,"nbFoyers":30911,"nbFoyersImposables":26905,"revenus":807441155,"revenusImposables":703597131,"impot":20048103,"nbFoyers_salaires":19676,"revenus_salaires":513024436,"nbFoyers_retraites":14019,"revenus_retraites":336316801},{"trancheName":"28 751 à 38 750","trancheMin":28751,"trancheMax":38750,"nbFoyers":41042,"nbFoyersImposables":38455,"revenus":1363875162,"revenusImposables":1279937041,"impot":50529038,"nbFoyers_salaires":27827,"revenus_salaires":913598599,"nbFoyers_retraites":17285,"revenus_retraites":493939457},{"trancheName":"38 751 à 48 750","trancheMin":38751,"trancheMax":48750,"nbFoyers":21952,"nbFoyersImposables":21274,"revenus":948233147,"revenusImposables":919165634,"impot":49863187,"nbFoyers_salaires":15196,"revenus_salaires":626897685,"nbFoyers_retraites":9110,"revenus_retraites":318749558},{"trancheName":"48 751 à 97 500","trancheMin":48751,"trancheMax":97500,"nbFoyers":24847,"nbFoyersImposables":24227,"revenus":1579635513,"revenusImposables":1539957824,"impot":130270137,"nbFoyers_salaires":17172,"revenus_salaires":947558257,"nbFoyers_retraites":9659,"revenus_retraites":431943987},{"trancheName":"+ de 97 500","trancheMin":97500,"trancheMax":0,"nbFoyers":5092,"nbFoyersImposables":4958,"revenus":889510195,"revenusImposables":868895511,"impot":136989547,"nbFoyers_salaires":3676,"revenus_salaires":326006625,"nbFoyers_retraites":1385,"revenus_retraites":65327849}],"nbFoyers":381344,"nbFoyersImposables":201949,"revenus":8583289412,"revenusImposables":6802276323,"impot":391845124,"nbFoyers_salaires":234686,"revenus_salaires":5462531004,"nbFoyers_retraites":146206,"revenus_retraites":2908979227},"2010":{"depNumber":"640","depName":"PYRENEES-ATLANTIQUES","year":2010,"tranches":[{"trancheName":"0 à 10 000","trancheMin":0,"trancheMax":10000,"nbFoyers":99722,"nbFoyersImposables":136,"revenus":494460459,"revenusImposables":608050,"impot":-11389914,"nbFoyers_salaires":43919,"revenus_salaires":301661104,"nbFoyers_retraites":38293,"revenus_retraites":328839071},{"trancheName":"10 001 à 12 000","trancheMin":10001,"trancheMax":12000,"nbFoyers":26294,"nbFoyersImposables":2250,"revenus":289640294,"revenusImposables":26268736,"impot":-6152707,"nbFoyers_salaires":16883,"revenus_salaires":210812125,"nbFoyers_retraites":9892,"revenus_retraites":127608676},{"trancheName":"12 001 à 15 000","trancheMin":12001,"trancheMax":15000,"nbFoyers":42513,"nbFoyersImposables":21008,"revenus":577650983,"revenusImposables":285759852,"impot":-3488083,"nbFoyers_salaires":30155,"revenus_salaires":456464519,"nbFoyers_retraites":13294,"revenus_retraites":197127404},{"trancheName":"15 001 à 20 000","trancheMin":15001,"trancheMax":20000,"nbFoyers":60815,"nbFoyersImposables":39821,"revenus":1052503127,"revenusImposables":693379229,"impot":16978090,"nbFoyers_salaires":40544,"revenus_salaires":748861807,"nbFoyers_retraites":22849,"revenus_retraites":415133088},{"trancheName":"20 001 à 30 000","trancheMin":20001,"trancheMax":30000,"nbFoyers":65412,"nbFoyersImposables":54919,"revenus":1612394646,"revenusImposables":1361762443,"impot":41901068,"nbFoyers_salaires":43449,"revenus_salaires":1075347872,"nbFoyers_retraites":27431,"revenus_retraites":627076984},{"trancheName":"30 001 à 50 000","trancheMin":30001,"trancheMax":50000,"nbFoyers":60308,"nbFoyersImposables":57313,"revenus":2290375285,"revenusImposables":2182425643,"impot":106106779,"nbFoyers_salaires":41305,"revenus_salaires":1527211058,"nbFoyers_retraites":25427,"revenus_retraites":800862047},{"trancheName":"50 001 à 100 000","trancheMin":50001,"trancheMax":100000,"nbFoyers":24841,"nbFoyersImposables":24133,"revenus":1617598901,"revenusImposables":1571230957,"impot":137295171,"nbFoyers_salaires":17211,"revenus_salaires":968582096,"nbFoyers_retraites":9706,"revenus_retraites":439611383},{"trancheName":"+ de 100 000","trancheMin":100000,"trancheMax":0,"nbFoyers":5149,"nbFoyersImposables":4996,"revenus":955901859,"revenusImposables":930052455,"impot":148538070,"nbFoyers_salaires":3719,"revenus_salaires":342627408,"nbFoyers_retraites":1461,"revenus_retraites":70581438}],"nbFoyers":385054,"nbFoyersImposables":204576,"revenus":8890525554,"revenusImposables":7051487365,"impot":429788474,"nbFoyers_salaires":237185,"revenus_salaires":5631567989,"nbFoyers_retraites":148353,"revenus_retraites":3006840091},"2011":{"depNumber":"640","depName":"PYRENEES-ATLANTIQUES","year":2011,"tranches":[{"trancheName":"0 à 10 000","trancheMin":0,"trancheMax":10000,"nbFoyers":89119,"nbFoyersImposables":224,"revenus":438446652,"revenusImposables":1130455,"impot":-8739664,"nbFoyers_salaires":37021,"revenus_salaires":253784707,"nbFoyers_retraites":35989,"revenus_retraites":311868372},{"trancheName":"10 001 à 12 000","trancheMin":10001,"trancheMax":12000,"nbFoyers":24327,"nbFoyersImposables":1962,"revenus":267964203,"revenusImposables":22878947,"impot":-5233915,"nbFoyers_salaires":15253,"revenus_salaires":190804034,"nbFoyers_retraites":9636,"revenus_retraites":125251897},{"trancheName":"12 001 à 15 000","trancheMin":12001,"trancheMax":15000,"nbFoyers":40370,"nbFoyersImposables":20377,"revenus":549292802,"revenusImposables":277623696,"impot":-2224289,"nbFoyers_salaires":28144,"revenus_salaires":429234998,"nbFoyers_retraites":13237,"revenus_retraites":198815160},{"trancheName":"15 001 à 20 000","trancheMin":15001,"trancheMax":20000,"nbFoyers":60650,"nbFoyersImposables":41380,"revenus":1050342193,"revenusImposables":720681615,"impot":21341105,"nbFoyers_salaires":40346,"revenus_salaires":751927827,"nbFoyers_retraites":22908,"revenus_retraites":418778892},{"trancheName":"20 001 à 30 000","trancheMin":20001,"trancheMax":30000,"nbFoyers":65935,"nbFoyersImposables":56044,"revenus":1626441318,"revenusImposables":1389995307,"impot":50098443,"nbFoyers_salaires":43398,"revenus_salaires":1081044198,"nbFoyers_retraites":27874,"revenus_retraites":647099775},{"trancheName":"30 001 à 50 000","trancheMin":30001,"trancheMax":50000,"nbFoyers":63276,"nbFoyersImposables":60125,"revenus":2409085785,"revenusImposables":2294737301,"impot":119549629,"nbFoyers_salaires":43291,"revenus_salaires":1610931477,"nbFoyers_retraites":26652,"revenus_retraites":849342580},{"trancheName":"50 001 à 100 000","trancheMin":50001,"trancheMax":100000,"nbFoyers":26982,"nbFoyersImposables":26150,"revenus":1758606634,"revenusImposables":1705046363,"impot":151172509,"nbFoyers_salaires":18806,"revenus_salaires":1064572283,"nbFoyers_retraites":10657,"revenus_retraites":485164051},{"trancheName":"+ de 100 000","trancheMin":100000,"trancheMax":0,"nbFoyers":5711,"nbFoyersImposables":5567,"revenus":1066453578,"revenusImposables":1043234885,"impot":172455977,"nbFoyers_salaires":4188,"revenus_salaires":396295706,"nbFoyers_retraites":1654,"revenus_retraites":81481301}],"nbFoyers":376370,"nbFoyersImposables":211829,"revenus":9166633165,"revenusImposables":7455328569,"impot":498419795,"nbFoyers_salaires":230447,"revenus_salaires":5778595230,"nbFoyers_retraites":148607,"revenus_retraites":3117802028},"2012":{"depNumber":"640","depName":"PYRENEES-ATLANTIQUES","year":2012,"tranches":[{"trancheName":"0 à 10 000","trancheMin":0,"trancheMax":10000,"nbFoyers":87953,"nbFoyersImposables":121,"revenus":429396169,"revenusImposables":685293,"impot":-7917262,"nbFoyers_salaires":36587,"revenus_salaires":250219035,"nbFoyers_retraites":34379,"revenus_retraites":298068847},{"trancheName":"10 001 à 12 000","trancheMin":10001,"trancheMax":12000,"nbFoyers":23724,"nbFoyersImposables":526,"revenus":261507237,"revenusImposables":6223890,"impot":-4322908,"nbFoyers_salaires":14361,"revenus_salaires":179248568,"nbFoyers_retraites":9847,"revenus_retraites":128842114},{"trancheName":"12 001 à 15 000","trancheMin":12001,"trancheMax":15000,"nbFoyers":39269,"nbFoyersImposables":22173,"revenus":534223786,"revenusImposables":303845559,"impot":-256230,"nbFoyers_salaires":27632,"revenus_salaires":421054503,"nbFoyers_retraites":12565,"revenus_retraites":188892511},{"trancheName":"15 001 à 20 000","trancheMin":15001,"trancheMax":20000,"nbFoyers":61867,"nbFoyersImposables":42265,"revenus":1071850430,"revenusImposables":735688003,"impot":25972458,"nbFoyers_salaires":41167,"revenus_salaires":767125460,"nbFoyers_retraites":23141,"revenus_retraites":425320505},{"trancheName":"20 001 à 30 000","trancheMin":20001,"trancheMax":30000,"nbFoyers":67201,"nbFoyersImposables":57182,"revenus":1655800277,"revenusImposables":1416776392,"impot":56389222,"nbFoyers_salaires":44138,"revenus_salaires":1099087323,"nbFoyers_retraites":28298,"revenus_retraites":659568680},{"trancheName":"30 001 à 50 000","trancheMin":30001,"trancheMax":50000,"nbFoyers":65194,"nbFoyersImposables":62043,"revenus":2486324694,"revenusImposables":2371363733,"impot":130918063,"nbFoyers_salaires":44048,"revenus_salaires":1638008558,"nbFoyers_retraites":27965,"revenus_retraites":896576436},{"trancheName":"50 001 à 100 000","trancheMin":50001,"trancheMax":100000,"nbFoyers":29164,"nbFoyersImposables":28206,"revenus":1904877009,"revenusImposables":1842061367,"impot":168756637,"nbFoyers_salaires":20204,"revenus_salaires":1139251981,"nbFoyers_retraites":11726,"revenus_retraites":541604672},{"trancheName":"+ de 100 000","trancheMin":100000,"trancheMax":0,"nbFoyers":6267,"nbFoyersImposables":6103,"revenus":1204305099,"revenusImposables":1180180217,"impot":204984427,"nbFoyers_salaires":4616,"revenus_salaires":434374230,"nbFoyers_retraites":1930,"revenus_retraites":98616515}],"nbFoyers":380639,"nbFoyersImposables":218619,"revenus":9548284701,"revenusImposables":7856824454,"impot":574524407,"nbFoyers_salaires":232753,"revenus_salaires":5928369658,"nbFoyers_retraites":149851,"revenus_retraites":3237490280}}}